rtl/alu.v
module alu (
    input  [3:0] alu_control,
    input  [31:0] src1,
    input  [31:0] src2,
    // OUT
    output reg [31:0] alu_result,
    output  zero,
    output less_than,
    output less_than_u
);


always @(*) begin
    case (alu_control)
        //ADD Operation
        4'b0000: alu_result = src1 + src2; 
        // Bitwise and operation
        4'b0010 : alu_result = src1 & src2;
        //OR operation
        4'b0011 : alu_result = src1 | src2;
        //Sub operation -> beq
        4'b0001 : alu_result = src1 + (~src2 + 1'b1); //2s complement representation
        //slti operation
        4'b0101 : alu_result = {31'b0, $signed(src1) < $signed(src2)};
        //sltiu operation
        4'b0111 : alu_result = {31'b0, src1 < src2};
        //xori operation
        4'b1000 : alu_result = src1 ^ src2;
        //shift left logical -> shamt is 5 bits
        4'b1001: alu_result = src1 << src2[4:0];
        //shift right logical 
        4'b1010: alu_result = src1 >> src2[4:0];
        //shift right arithmetic with sign preserved
        4'b1011: alu_result = $signed(src1) >>> src2[4:0];
        default: alu_result = 32'b0;
    endcase
end

assign zero = (alu_result == 32'b0);
//For blt instruction
assign less_than = ($signed(src1) < $signed(src2));
//BLTU unsigned
assign less_than_u = (src1 < src2);
    
endmodule

tb/tb_alu.v
`timescale 1ns/1ps
`include "../rtl/alu.v"

module tb_alu;

    reg  [3:0]  alu_control;
    reg  [31:0] src1;
    reg  [31:0] src2;

    wire [31:0] alu_result;
    wire        zero;
    wire        less_than;
    wire        less_than_u;

    alu dut (
        .alu_control (alu_control),
        .src1        (src1),
        .src2        (src2),
        .alu_result  (alu_result),
        .zero        (zero),
        .less_than   (less_than),
        .less_than_u (less_than_u)
    );

    initial begin

        $dumpfile("alu_wave.vcd");
        $dumpvars(0, tb_alu);

        src1 = 10;
        src2 = 5;

        alu_control = 4'b0000; #10;
        $display("ADD  : src1=%0d src2=%0d result=%0d", src1, src2, alu_result);

        alu_control = 4'b0001; #10;
        $display("SUB  : src1=%0d src2=%0d result=%0d", src1, src2, alu_result);

        alu_control = 4'b0010; #10;
        $display("AND  : src1=%0d src2=%0d result=%0d", src1, src2, alu_result);

        alu_control = 4'b0011; #10;
        $display("OR   : src1=%0d src2=%0d result=%0d", src1, src2, alu_result);

        alu_control = 4'b1000; #10;
        $display("XOR  : src1=%0d src2=%0d result=%0d", src1, src2, alu_result);

        alu_control = 4'b0101; #10;
        $display("SLT  : src1=%0d src2=%0d result=%0d", src1, src2, alu_result);

        alu_control = 4'b0111; #10;
        $display("SLTU : src1=%0d src2=%0d result=%0d", src1, src2, alu_result);

        src1 = 8;
        src2 = 2;

        alu_control = 4'b1001; #10;
        $display("SLL  : src1=%0d src2=%0d result=%0d", src1, src2, alu_result);

        alu_control = 4'b1010; #10;
        $display("SRL  : src1=%0d src2=%0d result=%0d", src1, src2, alu_result);

        src1 = 32'hFFFF_FFF0;
        src2 = 2;

        alu_control = 4'b1011; #10;
        $display("SRA  : src1=%h src2=%0d result=%h", src1, src2, alu_result);

        src1 = 5;
        src2 = 5;

        alu_control = 4'b0001; #10;
        $display("ZERO : src1=%0d src2=%0d result=%0d zero=%b",
                 src1, src2, alu_result, zero);

        src1 = -5;
        src2 = 3;

        alu_control = 4'b0101; #10;
        $display("SLT Signed : src1=%0d src2=%0d result=%0d",
                 $signed(src1), $signed(src2), alu_result);

        src1 = 32'hFFFF_FFFF;
        src2 = 1;

        alu_control = 4'b0111; #10;
        $display("SLTU Unsigned : src1=%h src2=%0d result=%0d",
                 src1, src2, alu_result);

        #10;
        $finish;
    end

endmodule

sim/alu_wave.vcd
$date
	Tue Jun  9 01:04:27 2026
$end
$version
	Icarus Verilog
$end
$timescale
	1ps
$end
$scope module tb_alu $end
$var wire 1 ! zero $end
$var wire 1 " less_than_u $end
$var wire 1 # less_than $end
$var wire 32 $ alu_result [31:0] $end
$var reg 4 % alu_control [3:0] $end
$var reg 32 & src1 [31:0] $end
$var reg 32 ' src2 [31:0] $end
$scope module dut $end
$var wire 4 ( alu_control [3:0] $end
$var wire 32 ) src1 [31:0] $end
$var wire 32 * src2 [31:0] $end
$var wire 1 ! zero $end
$var wire 1 " less_than_u $end
$var wire 1 # less_than $end
$var reg 32 + alu_result [31:0] $end
$upscope $end
$upscope $end
$enddefinitions $end
$comment Show the parameter values. $end
$dumpall
$end
#0
$dumpvars
b1111 +
b101 *
b1010 )
b0 (
b101 '
b1010 &
b0 %
b1111 $
0#
0"
0!
$end
#10000
b101 $
b101 +
b1 %
b1 (
#20000
1!
b0 $
b0 +
b10 %
b10 (
#30000
0!
b1111 $
b1111 +
b11 %
b11 (
#40000
b1000 %
b1000 (
#50000
1!
b0 $
b0 +
b101 %
b101 (
#60000
b111 %
b111 (
#70000
0!
b100000 $
b100000 +
b1001 %
b1001 (
b10 '
b10 *
b1000 &
b1000 )
#80000
b10 $
b10 +
b1010 %
b1010 (
#90000
b11111111111111111111111111111100 $
b11111111111111111111111111111100 +
b1011 %
b1011 (
1#
b11111111111111111111111111110000 &
b11111111111111111111111111110000 )
#100000
1!
b0 $
b0 +
b1 %
b1 (
b101 '
b101 *
0#
b101 &
b101 )
#110000
0!
b1 $
b1 +
b101 %
b101 (
b11 '
b11 *
1#
b11111111111111111111111111111011 &
b11111111111111111111111111111011 )
#120000
1!
b0 $
b0 +
b111 %
b111 (
b1 '
b1 *
b11111111111111111111111111111111 &
b11111111111111111111111111111111 )
