rtl/control.v
module control (
    input  [6:0] op,
    input  [2:0] func3,
    input  [6:0] func7,

    //OUT
    output reg [3:0] alu_control,
    output reg [2:0] imm_source,
    output reg mem_write,
    output reg  reg_write,
    //added for R type instruction
    output reg alu_source,
    output reg [1:0] write_back_source,
    //for U type 
    output reg second_add_source,
    output reg branch,
    output reg jump,
    output reg jalr
);


/////////////////////////////////
///Main decoder to compute alu_op///
////////////////////////////////////

reg [1:0] alu_op;


always @(*) begin

    // defaults values
    reg_write         = 1'b0;
    imm_source        = 3'b000;
    mem_write         = 1'b0;
    alu_op            = 2'b00;
    alu_source        = 1'b0;
    write_back_source = 2'b00;
    second_add_source = 1'b0;
    branch            = 1'b0;
    jump              = 1'b0;
    jalr              = 1'b0;

    case (op)

    //LW , I type
        7'b0000011 : begin
            reg_write = 1'b1;
            imm_source = 3'b000;
            mem_write = 1'b0;
            alu_op = 2'b00;
            alu_source = 1'b1;
            write_back_source = 2'b01; 
            branch = 1'b0;
            jump = 1'b0;
        end
    //SW , S type
        7'b0100011 : begin
            reg_write = 1'b0;
            imm_source = 3'b001;
            mem_write = 1'b1;
            alu_op = 2'b00;
            alu_source = 1'b1;
            branch = 1'b0;
            jump = 1'b0;
        end

    //R Type -> add , or , and
        7'b0110011 : begin
            reg_write = 1'b1;
            mem_write = 1'b0;
            alu_op = 2'b10;
            alu_source = 1'b0; //take reg2 instead of immediate
            write_back_source = 2'b00; // take the alu_result instead of memory value
            branch = 1'b0;
            jump = 1'b0;
        end

    //B Type -> beq
        7'b1100011 : begin
            reg_write = 1'b0;
            imm_source = 3'b010;
            alu_source = 1'b0;
            mem_write = 1'b0;
            alu_op = 2'b01;
            branch = 1'b1;
            jump = 1'b0;
            //modified while adding u type
            second_add_source = 1'b0;
        end

    //J Type -> jal
        7'b1101111 : begin
            reg_write = 1'b1;
            imm_source = 3'b011;
            mem_write = 1'b0;
            write_back_source = 2'b10; //store pc = pc+4 into a destination register
            branch = 1'b0;
            jump = 1'b1;
            //modifed while adding u type
            second_add_source = 1'b0;
        end

    //I type - ALU instructions : addi
        7'b0010011 : begin
            reg_write = 1'b1;
            imm_source = 3'b000;
            alu_source = 1'b1; // select immediate as src2 of ALU
            mem_write = 1'b0;
            alu_op = 2'b10; //R type instr
            write_back_source = 2'b00; //write back the ALU Result to the dest reg
            branch = 1'b0;
            jump = 1'b0;
        end

    // U Type instructions : lui and auipc
        7'b0110111, 7'b0010111 : begin
            imm_source = 3'b100;
            mem_write = 1'b0;
            reg_write = 1'b1;
            write_back_source = 2'b00;
            branch = 1'b0;
            jump = 1'b0;
            alu_source = 1'b1;
            alu_op = 2'b00;
            if (op == 7'b0110111)
                second_add_source = 1'b1; // LUI → immediate only
            else
                second_add_source = 1'b0; // AUIPC → PC + immediate
        end

    //JALR 

        7'b1100111 : begin
            reg_write = 1'b1;
            imm_source = 3'b000;        // I-type immediate
            mem_write = 1'b0;
            write_back_source = 2'b10;  // rd = PC + 4
            branch = 1'b0;
            jump   = 1'b0;
            // JALR signal is 1
            jalr = 1'b1;
            alu_op = 2'b00;
            alu_source = 1'b1;
            second_add_source = 1'b0;
        end

        default: begin
            reg_write = 1'b0;
            imm_source = 3'b000;
            mem_write = 1'b0;
            alu_op = 2'b00;
            alu_source = 1'b0;
            branch = 1'b0;
            jump = 1'b0;
        end
    endcase
end

////////////////////////////////////
//ALU DECODER to compute alu_control
////////////////////////////////////

always @(*) begin
    case (alu_op)
    //LW and SW , ALU has to add
        2'b00 : alu_control = 4'b0000;
    //R Type instruction , ALU Operation is dependent on func3, func7
        2'b10 : begin
            case (func3)
                // ADD and SUB have same funct3 but diff is at funct7
                3'b000 : begin
                    if ((op == 7'b0110011) && (func7 == 7'b0100000))
                        alu_control = 4'b0001;   // SUB
                    else
                        alu_control = 4'b0000;   // ADD and ADDI
                end
                //AND
                3'b111 : alu_control = 4'b0010;
                //OR instruction
                3'b110 : alu_control = 4'b0011;
                //SLTI instruction
                3'b010 : alu_control = 4'b0101;
                //SLTU Instruction
                3'b011 : alu_control = 4'b0111;
                //xor
                3'b100 : alu_control = 4'b1000;
                //SLLI instruction
                3'b001 : alu_control = 4'b1001;

                //SRLI / SRAI (and SRL / SRA) have same funct3 they are difference by funct7
                3'b101 : begin
                    if (func7 == 7'b0100000)
                        alu_control = 4'b1011;  // SRAI (arithmetic shift right)
                    else
                        alu_control = 4'b1010;  // SRLI (logical shift right)
                    end
                // ALL THE OTHERS
                default: alu_control = 4'b0000;
            endcase
        end
    //REST OF THE INSTRUCTIONS
    //B type -> beq
        //ALU Has to sub to compare reg1 , reg2
        2'b01 : begin
            //Based on func3 we can differentiate Branch instructions
            case (func3)
                3'b000 : alu_control = 4'b0001;  // BEQ
                3'b001 : alu_control = 4'b0001;  // BNE
                3'b100 : alu_control = 4'b0101;  // BLT
                3'b101 : alu_control = 4'b0101;  // BGE
                3'b110 : alu_control = 4'b0111;  // BLTU
                3'b111 : alu_control = 4'b0111;  // BGEU
                default: alu_control = 4'b0001;
            endcase
        end

        default: alu_control = 4'b0111;
    endcase
end




endmodule

tb/tb_control.v
`timescale 1ns/1ps
`include "../rtl/control.v"

module tb_control;

    reg  [6:0] op;
    reg  [2:0] func3;
    reg  [6:0] func7;

    wire [3:0] alu_control;
    wire [2:0] imm_source;
    wire       mem_write;
    wire       reg_write;
    wire       alu_source;
    wire [1:0] write_back_source;
    wire       second_add_source;
    wire       branch;
    wire       jump;
    wire       jalr;

    control dut (
        .op                (op),
        .func3             (func3),
        .func7             (func7),
        .alu_control       (alu_control),
        .imm_source        (imm_source),
        .mem_write         (mem_write),
        .reg_write         (reg_write),
        .alu_source        (alu_source),
        .write_back_source (write_back_source),
        .second_add_source (second_add_source),
        .branch            (branch),
        .jump              (jump),
        .jalr              (jalr)
    );

    initial begin
        $dumpfile("../sim/control_wave.vcd");
        $dumpvars(0, tb_control);

        op = 7'b0000011; func3 = 3'b010; func7 = 7'b0000000; #20;
        $display("LW    : alu_control=%b imm_source=%b mem_write=%b reg_write=%b alu_source=%b wb_src=%b branch=%b jump=%b jalr=%b",
                 alu_control, imm_source, mem_write, reg_write, alu_source, write_back_source, branch, jump, jalr);

        op = 7'b0100011; func3 = 3'b010; func7 = 7'b0000000; #20;
        $display("SW    : alu_control=%b imm_source=%b mem_write=%b reg_write=%b alu_source=%b wb_src=%b branch=%b jump=%b jalr=%b",
                 alu_control, imm_source, mem_write, reg_write, alu_source, write_back_source, branch, jump, jalr);

        op = 7'b0110011; func3 = 3'b000; func7 = 7'b0000000; #20;
        $display("ADD   : alu_control=%b imm_source=%b mem_write=%b reg_write=%b alu_source=%b wb_src=%b branch=%b jump=%b jalr=%b",
                 alu_control, imm_source, mem_write, reg_write, alu_source, write_back_source, branch, jump, jalr);

        op = 7'b0110011; func3 = 3'b000; func7 = 7'b0100000; #20;
        $display("SUB   : alu_control=%b imm_source=%b mem_write=%b reg_write=%b alu_source=%b wb_src=%b branch=%b jump=%b jalr=%b",
                 alu_control, imm_source, mem_write, reg_write, alu_source, write_back_source, branch, jump, jalr);

        op = 7'b0110011; func3 = 3'b111; func7 = 7'b0000000; #20;
        $display("AND   : alu_control=%b imm_source=%b mem_write=%b reg_write=%b alu_source=%b wb_src=%b branch=%b jump=%b jalr=%b",
                 alu_control, imm_source, mem_write, reg_write, alu_source, write_back_source, branch, jump, jalr);

        op = 7'b0110011; func3 = 3'b110; func7 = 7'b0000000; #20;
        $display("OR    : alu_control=%b imm_source=%b mem_write=%b reg_write=%b alu_source=%b wb_src=%b branch=%b jump=%b jalr=%b",
                 alu_control, imm_source, mem_write, reg_write, alu_source, write_back_source, branch, jump, jalr);

        op = 7'b0010011; func3 = 3'b000; func7 = 7'b0000000; #20;
        $display("ADDI  : alu_control=%b imm_source=%b mem_write=%b reg_write=%b alu_source=%b wb_src=%b branch=%b jump=%b jalr=%b",
                 alu_control, imm_source, mem_write, reg_write, alu_source, write_back_source, branch, jump, jalr);

        op = 7'b0010011; func3 = 3'b010; func7 = 7'b0000000; #20;
        $display("SLTI  : alu_control=%b imm_source=%b mem_write=%b reg_write=%b alu_source=%b wb_src=%b branch=%b jump=%b jalr=%b",
                 alu_control, imm_source, mem_write, reg_write, alu_source, write_back_source, branch, jump, jalr);

        op = 7'b1100011; func3 = 3'b000; func7 = 7'b0000000; #20;
        $display("BEQ   : alu_control=%b imm_source=%b mem_write=%b reg_write=%b alu_source=%b wb_src=%b branch=%b jump=%b jalr=%b",
                 alu_control, imm_source, mem_write, reg_write, alu_source, write_back_source, branch, jump, jalr);

        op = 7'b1100011; func3 = 3'b001; func7 = 7'b0000000; #20;
        $display("BNE   : alu_control=%b imm_source=%b mem_write=%b reg_write=%b alu_source=%b wb_src=%b branch=%b jump=%b jalr=%b",
                 alu_control, imm_source, mem_write, reg_write, alu_source, write_back_source, branch, jump, jalr);

        op = 7'b1101111; func3 = 3'b000; func7 = 7'b0000000; #20;
        $display("JAL   : alu_control=%b imm_source=%b mem_write=%b reg_write=%b alu_source=%b wb_src=%b branch=%b jump=%b jalr=%b",
                 alu_control, imm_source, mem_write, reg_write, alu_source, write_back_source, branch, jump, jalr);

        op = 7'b1100111; func3 = 3'b000; func7 = 7'b0000000; #20;
        $display("JALR  : alu_control=%b imm_source=%b mem_write=%b reg_write=%b alu_source=%b wb_src=%b branch=%b jump=%b jalr=%b",
                 alu_control, imm_source, mem_write, reg_write, alu_source, write_back_source, branch, jump, jalr);

        op = 7'b0110111; func3 = 3'b000; func7 = 7'b0000000; #20;
        $display("LUI   : alu_control=%b imm_source=%b mem_write=%b reg_write=%b alu_source=%b wb_src=%b second_add_source=%b branch=%b jump=%b jalr=%b",
                 alu_control, imm_source, mem_write, reg_write, alu_source, write_back_source, second_add_source, branch, jump, jalr);

        op = 7'b0010111; func3 = 3'b000; func7 = 7'b0000000; #20;
        $display("AUIPC : alu_control=%b imm_source=%b mem_write=%b reg_write=%b alu_source=%b wb_src=%b second_add_source=%b branch=%b jump=%b jalr=%b",
                 alu_control, imm_source, mem_write, reg_write, alu_source, write_back_source, second_add_source, branch, jump, jalr);

        #20;
        $finish;
    end

endmodule

sim/control_wave.vcd
$date
	Sat Jun 13 19:32:58 2026
$end
$version
	Icarus Verilog
$end
$timescale
	1ps
$end
$scope module tb_control $end
$var wire 2 ! write_back_source [1:0] $end
$var wire 1 " second_add_source $end
$var wire 1 # reg_write $end
$var wire 1 $ mem_write $end
$var wire 1 % jump $end
$var wire 1 & jalr $end
$var wire 3 ' imm_source [2:0] $end
$var wire 1 ( branch $end
$var wire 1 ) alu_source $end
$var wire 4 * alu_control [3:0] $end
$var reg 3 + func3 [2:0] $end
$var reg 7 , func7 [6:0] $end
$var reg 7 - op [6:0] $end
$scope module dut $end
$var wire 3 . func3 [2:0] $end
$var wire 7 / func7 [6:0] $end
$var wire 7 0 op [6:0] $end
$var reg 4 1 alu_control [3:0] $end
$var reg 2 2 alu_op [1:0] $end
$var reg 1 ) alu_source $end
$var reg 1 ( branch $end
$var reg 3 3 imm_source [2:0] $end
$var reg 1 & jalr $end
$var reg 1 % jump $end
$var reg 1 $ mem_write $end
$var reg 1 # reg_write $end
$var reg 1 " second_add_source $end
$var reg 2 4 write_back_source [1:0] $end
$upscope $end
$upscope $end
$enddefinitions $end
$comment Show the parameter values. $end
$dumpall
$end
#0
$dumpvars
b1 4
b0 3
b0 2
b0 1
b11 0
b0 /
b10 .
b11 -
b0 ,
b10 +
b0 *
1)
0(
b0 '
0&
0%
0$
1#
0"
b1 !
$end
#20000
1$
b1 '
b1 3
b0 !
b0 4
1)
0#
b100011 -
b100011 0
#40000
b10 2
1#
0)
0$
b0 '
b0 3
b0 +
b0 .
b110011 -
b110011 0
#60000
b1 *
b1 1
b100000 ,
b100000 /
#80000
b10 *
b10 1
b0 ,
b0 /
b111 +
b111 .
#100000
b11 *
b11 1
b110 +
b110 .
#120000
b0 *
b0 1
1)
b10 2
1#
b0 +
b0 .
b10011 -
b10011 0
#140000
b101 *
b101 1
b10 +
b10 .
#160000
b1 *
b1 1
1(
b10 '
b10 3
0)
b1 2
0#
b0 +
b0 .
b1100011 -
b1100011 0
#180000
b1 +
b1 .
#200000
b0 *
b0 1
1%
b10 !
b10 4
1#
0(
b0 2
b11 '
b11 3
b0 +
b0 .
b1101111 -
b1101111 0
#220000
1)
1&
0%
b10 !
b10 4
b0 '
b0 3
1#
b1100111 -
b1100111 0
#240000
1"
b100 '
b100 3
0&
b0 !
b0 4
1)
1#
b110111 -
b110111 0
#260000
0"
1)
b100 '
b100 3
1#
b10111 -
b10111 0
