rtl/dmem.v
module dmem (
    input  wire        clk,
    input  wire        rst_n,
    input  wire [31:0] address,
    input  wire [31:0] write_data,
    input  wire        write_enable,
    output wire [31:0] read_data
);

    integer i;
    reg [31:0] mem [0:63];

    always @(posedge clk) begin
        if (!rst_n) begin
            for (i = 0; i < 64; i = i + 1)
                mem[i] <= 32'b0;
        end
        else if (write_enable) begin
            if (address[1:0] == 2'b00)
                mem[address[31:2]] <= write_data;
        end
    end

    assign read_data = mem[address[31:2]];

endmodule

tb/tb_dmem.v
`timescale 1ns/1ps
`include "../rtl/dmem.v"

module tb_dmem;

    reg         clk;
    reg         rst_n;
    reg  [31:0] address;
    reg  [31:0] write_data;
    reg         write_enable;
    wire [31:0] read_data;

    dmem dut (
        .clk          (clk),
        .rst_n        (rst_n),
        .address      (address),
        .write_data   (write_data),
        .write_enable (write_enable),
        .read_data    (read_data)
    );

    always #5 clk = ~clk;

    initial begin
        $dumpfile("dmem_wave.vcd");
        $dumpvars(0, tb_dmem);

        clk = 0;
        rst_n = 0;
        address = 0;
        write_data = 0;
        write_enable = 0;

        #20;
        rst_n = 1;

        address = 32'd0;
        write_data = 32'hAAAA_1111;
        write_enable = 1;
        #10;
        write_enable = 0;
        #10;
        $display("WRITE/READ address=%0d data=%h", address, read_data);

        address = 32'd4;
        write_data = 32'hBBBB_2222;
        write_enable = 1;
        #10;
        write_enable = 0;
        #10;
        $display("WRITE/READ address=%0d data=%h", address, read_data);

        address = 32'd8;
        write_data = 32'hCCCC_3333;
        write_enable = 1;
        #10;
        write_enable = 0;
        #10;
        $display("WRITE/READ address=%0d data=%h", address, read_data);

        address = 32'd0;
        #20;
        $display("READ address=%0d data=%h", address, read_data);

        address = 32'd4;
        #20;
        $display("READ address=%0d data=%h", address, read_data);

        address = 32'd8;
        #20;
        $display("READ address=%0d data=%h", address, read_data);

        #20;
        $finish;
    end

endmodule

sim/dmem_wave.vcd
$date
	Sat Jun 13 12:10:33 2026
$end
$version
	Icarus Verilog
$end
$timescale
	1ps
$end
$scope module tb_dmem $end
$var wire 32 ! read_data [31:0] $end
$var reg 32 " address [31:0] $end
$var reg 1 # clk $end
$var reg 1 $ rst_n $end
$var reg 32 % write_data [31:0] $end
$var reg 1 & write_enable $end
$scope module dut $end
$var wire 32 ' address [31:0] $end
$var wire 1 # clk $end
$var wire 32 ( read_data [31:0] $end
$var wire 1 $ rst_n $end
$var wire 32 ) write_data [31:0] $end
$var wire 1 & write_enable $end
$var integer 32 * i [31:0] $end
$upscope $end
$upscope $end
$enddefinitions $end
$comment Show the parameter values. $end
$dumpall
$end
#0
$dumpvars
bx *
b0 )
bx (
b0 '
0&
b0 %
0$
0#
b0 "
bx !
$end
#5000
b0 !
b0 (
b1000000 *
1#
#10000
0#
#15000
b1000000 *
1#
#20000
0#
1&
b10101010101010100001000100010001 %
b10101010101010100001000100010001 )
1$
#25000
b10101010101010100001000100010001 !
b10101010101010100001000100010001 (
1#
#30000
0#
0&
#35000
1#
#40000
b0 !
b0 (
0#
1&
b10111011101110110010001000100010 %
b10111011101110110010001000100010 )
b100 "
b100 '
#45000
b10111011101110110010001000100010 !
b10111011101110110010001000100010 (
1#
#50000
0#
0&
#55000
1#
#60000
b0 !
b0 (
0#
1&
b11001100110011000011001100110011 %
b11001100110011000011001100110011 )
b1000 "
b1000 '
#65000
b11001100110011000011001100110011 !
b11001100110011000011001100110011 (
1#
#70000
0#
0&
#75000
1#
#80000
b10101010101010100001000100010001 !
b10101010101010100001000100010001 (
0#
b0 "
b0 '
#85000
1#
#90000
0#
#95000
1#
#100000
b10111011101110110010001000100010 !
b10111011101110110010001000100010 (
0#
b100 "
b100 '
#105000
1#
#110000
0#
#115000
1#
#120000
b11001100110011000011001100110011 !
b11001100110011000011001100110011 (
0#
b1000 "
b1000 '
