rtl/alu.v
module alu (
    input  [3:0] alu_control,
    input  [31:0] src1,
    input  [31:0] src2,
    // OUT
    output reg [31:0] alu_result,
    output  zero,
    output less_than,
    output less_than_u
);


always @(*) begin
    case (alu_control)
        //ADD Operation
        4'b0000: alu_result = src1 + src2; 
        // Bitwise and operation
        4'b0010 : alu_result = src1 & src2;
        //OR operation
        4'b0011 : alu_result = src1 | src2;
        //Sub operation -> beq
        4'b0001 : alu_result = src1 + (~src2 + 1'b1); //2s complement representation
        //slti operation
        4'b0101 : alu_result = {31'b0, $signed(src1) < $signed(src2)};
        //sltiu operation
        4'b0111 : alu_result = {31'b0, src1 < src2};
        //xori operation
        4'b1000 : alu_result = src1 ^ src2;
        //shift left logical -> shamt is 5 bits
        4'b1001: alu_result = src1 << src2[4:0];
        //shift right logical 
        4'b1010: alu_result = src1 >> src2[4:0];
        //shift right arithmetic with sign preserved
        4'b1011: alu_result = $signed(src1) >>> src2[4:0];
        default: alu_result = 32'b0;
    endcase
end

assign zero = (alu_result == 32'b0);
//For blt instruction
assign less_than = ($signed(src1) < $signed(src2));
//BLTU unsigned
assign less_than_u = (src1 < src2);
    
endmodule

rtl/ex_stage.v
module ex_stage (
    input  wire        clk,
    input  wire        rst_n,

    input  wire [31:0] id_ex_pc,
    input  wire [31:0] id_ex_pc4,
    input  wire [31:0] id_ex_rdata1,
    input  wire [31:0] id_ex_rdata2,
    input  wire [31:0] id_ex_imm,

    input  wire [3:0]  id_ex_alu_control,
    input  wire        id_ex_alu_source,

    input  wire [1:0]  id_ex_write_back_source,
    input  wire        id_ex_mem_write,
    input  wire        id_ex_reg_write,

    input  wire        id_ex_branch,
    input  wire        id_ex_jump,
    input  wire        id_ex_jalr,

    input  wire [6:0]  id_ex_op,
    input  wire [2:0]  id_ex_f3,
    input  wire [6:0]  id_ex_f7,
    input  wire [4:0]  id_ex_rs1,
    input  wire [4:0]  id_ex_rs2,
    input  wire [4:0]  id_ex_rd,

    // Forwarding control
    input  wire [1:0]  forward_a,
    input  wire [1:0]  forward_b,

    // Forwarded data from later stages
    input  wire [31:0] ex_mem_forward_data,
    input  wire [31:0] wb_forward_data,

    output reg  [31:0] ex_mem_alu_result,
    output reg  [31:0] ex_mem_rdata2,
    output reg  [1:0]  ex_mem_write_back_source,
    output reg         ex_mem_mem_write,
    output reg         ex_mem_reg_write,
    output reg  [4:0]  ex_mem_rd,
    output reg  [31:0] ex_mem_pc4,

    output wire        ex_pc_src,
    output wire [31:0] ex_pc_target
);

    // For AUIPC/LUI handling
    wire is_lui;
    wire is_auipc;

    assign is_lui   = (id_ex_op == 7'b0110111);
    assign is_auipc = (id_ex_op == 7'b0010111);

    // Forwarded register operands
    reg [31:0] forwarded_rs1;
    reg [31:0] forwarded_rs2;

    always @(*) begin
        case (forward_a)
            2'b00: forwarded_rs1 = id_ex_rdata1;
            2'b10: forwarded_rs1 = ex_mem_forward_data;
            2'b01: forwarded_rs1 = wb_forward_data;
            default: forwarded_rs1 = id_ex_rdata1;
        endcase
    end

    always @(*) begin
        case (forward_b)
            2'b00: forwarded_rs2 = id_ex_rdata2;
            2'b10: forwarded_rs2 = ex_mem_forward_data;
            2'b01: forwarded_rs2 = wb_forward_data;
            default: forwarded_rs2 = id_ex_rdata2;
        endcase
    end

    // Final ALU inputs after forwarding
    wire [31:0] alu_src1;
    wire [31:0] alu_src2;

    assign alu_src1 = is_lui   ? 32'b0 :
                      is_auipc ? id_ex_pc :
                                 forwarded_rs1;

    assign alu_src2 = id_ex_alu_source ? id_ex_imm : forwarded_rs2;

    wire [31:0] alu_result;
    wire        zero;
    wire        less_than;
    wire        less_than_u;

    alu ALU (
        .alu_control(id_ex_alu_control),
        .src1(alu_src1),
        .src2(alu_src2),
        .alu_result(alu_result),
        .zero(zero),
        .less_than(less_than),
        .less_than_u(less_than_u)
    );

    // Branch taken logic
    wire branch_taken;

    assign branch_taken =
        id_ex_branch & (
            (id_ex_f3 == 3'b000 &&  zero)        |  // BEQ
            (id_ex_f3 == 3'b001 && !zero)        |  // BNE
            (id_ex_f3 == 3'b100 &&  less_than)   |  // BLT
            (id_ex_f3 == 3'b101 && !less_than)   |  // BGE
            (id_ex_f3 == 3'b110 &&  less_than_u) |  // BLTU
            (id_ex_f3 == 3'b111 && !less_than_u)    // BGEU
        );

    assign ex_pc_src = id_ex_jump | id_ex_jalr | branch_taken;

    assign ex_pc_target =
        id_ex_jump ? (id_ex_pc + id_ex_imm) :
        id_ex_jalr ? ((forwarded_rs1 + id_ex_imm) & ~32'd1) :
                     (id_ex_pc + id_ex_imm);

    // EX/MEM pipeline register
    always @(posedge clk) begin
        if (!rst_n) begin
            ex_mem_alu_result        <= 32'b0;
            ex_mem_rdata2            <= 32'b0;
            ex_mem_write_back_source <= 2'b0;
            ex_mem_mem_write         <= 1'b0;
            ex_mem_reg_write         <= 1'b0;
            ex_mem_rd                <= 5'b0;
            ex_mem_pc4               <= 32'b0;
        end
        else begin
            ex_mem_alu_result        <= alu_result;
            ex_mem_rdata2            <= forwarded_rs2;
            ex_mem_write_back_source <= id_ex_write_back_source;
            ex_mem_mem_write         <= id_ex_mem_write;
            ex_mem_reg_write         <= id_ex_reg_write;
            ex_mem_rd                <= id_ex_rd;
            ex_mem_pc4               <= id_ex_pc4;
        end
    end

endmodule

tb/tb_ex_stage.v
`timescale 1ns/1ps

`include "../rtl/alu.v"
`include "../rtl/ex_stage.v"

module tb_ex_stage;

    reg clk;
    reg rst_n;

    reg [31:0] id_ex_pc;
    reg [31:0] id_ex_pc4;
    reg [31:0] id_ex_rdata1;
    reg [31:0] id_ex_rdata2;
    reg [31:0] id_ex_imm;

    reg [3:0]  id_ex_alu_control;
    reg        id_ex_alu_source;

    reg [1:0]  id_ex_write_back_source;
    reg        id_ex_mem_write;
    reg        id_ex_reg_write;

    reg        id_ex_branch;
    reg        id_ex_jump;
    reg        id_ex_jalr;

    reg [6:0]  id_ex_op;
    reg [2:0]  id_ex_f3;
    reg [6:0]  id_ex_f7;
    reg [4:0]  id_ex_rs1;
    reg [4:0]  id_ex_rs2;
    reg [4:0]  id_ex_rd;

    reg [1:0]  forward_a;
    reg [1:0]  forward_b;
    reg [31:0] ex_mem_forward_data;
    reg [31:0] wb_forward_data;

    wire [31:0] ex_mem_alu_result;
    wire [31:0] ex_mem_rdata2;
    wire [1:0]  ex_mem_write_back_source;
    wire        ex_mem_mem_write;
    wire        ex_mem_reg_write;
    wire [4:0]  ex_mem_rd;
    wire [31:0] ex_mem_pc4;

    wire        ex_pc_src;
    wire [31:0] ex_pc_target;

    ex_stage dut (
        .clk                      (clk),
        .rst_n                    (rst_n),

        .id_ex_pc                 (id_ex_pc),
        .id_ex_pc4                (id_ex_pc4),
        .id_ex_rdata1             (id_ex_rdata1),
        .id_ex_rdata2             (id_ex_rdata2),
        .id_ex_imm                (id_ex_imm),

        .id_ex_alu_control        (id_ex_alu_control),
        .id_ex_alu_source         (id_ex_alu_source),

        .id_ex_write_back_source  (id_ex_write_back_source),
        .id_ex_mem_write          (id_ex_mem_write),
        .id_ex_reg_write          (id_ex_reg_write),

        .id_ex_branch             (id_ex_branch),
        .id_ex_jump               (id_ex_jump),
        .id_ex_jalr               (id_ex_jalr),

        .id_ex_op                 (id_ex_op),
        .id_ex_f3                 (id_ex_f3),
        .id_ex_f7                 (id_ex_f7),
        .id_ex_rs1                (id_ex_rs1),
        .id_ex_rs2                (id_ex_rs2),
        .id_ex_rd                 (id_ex_rd),

        .forward_a                (forward_a),
        .forward_b                (forward_b),
        .ex_mem_forward_data      (ex_mem_forward_data),
        .wb_forward_data          (wb_forward_data),

        .ex_mem_alu_result        (ex_mem_alu_result),
        .ex_mem_rdata2            (ex_mem_rdata2),
        .ex_mem_write_back_source (ex_mem_write_back_source),
        .ex_mem_mem_write         (ex_mem_mem_write),
        .ex_mem_reg_write         (ex_mem_reg_write),
        .ex_mem_rd                (ex_mem_rd),
        .ex_mem_pc4               (ex_mem_pc4),

        .ex_pc_src                (ex_pc_src),
        .ex_pc_target             (ex_pc_target)
    );

    always #5 clk = ~clk;

    initial begin
        $dumpfile("../sim/ex_stage_wave.vcd");
        $dumpvars(0, tb_ex_stage);

        clk = 0;
        rst_n = 0;

        id_ex_pc = 0;
        id_ex_pc4 = 0;
        id_ex_rdata1 = 0;
        id_ex_rdata2 = 0;
        id_ex_imm = 0;

        id_ex_alu_control = 0;
        id_ex_alu_source = 0;

        id_ex_write_back_source = 0;
        id_ex_mem_write = 0;
        id_ex_reg_write = 0;

        id_ex_branch = 0;
        id_ex_jump = 0;
        id_ex_jalr = 0;

        id_ex_op = 0;
        id_ex_f3 = 0;
        id_ex_f7 = 0;
        id_ex_rs1 = 0;
        id_ex_rs2 = 0;
        id_ex_rd = 0;

        forward_a = 2'b00;
        forward_b = 2'b00;
        ex_mem_forward_data = 0;
        wb_forward_data = 0;

        #20;
        rst_n = 1;

        id_ex_pc = 32'd0;
        id_ex_pc4 = 32'd4;
        id_ex_rdata1 = 32'd10;
        id_ex_rdata2 = 32'd20;
        id_ex_imm = 32'd0;
        id_ex_alu_control = 4'b0000;
        id_ex_alu_source = 1'b0;
        id_ex_write_back_source = 2'b00;
        id_ex_mem_write = 1'b0;
        id_ex_reg_write = 1'b1;
        id_ex_branch = 1'b0;
        id_ex_jump = 1'b0;
        id_ex_jalr = 1'b0;
        id_ex_op = 7'b0110011;
        id_ex_f3 = 3'b000;
        id_ex_f7 = 7'b0000000;
        id_ex_rs1 = 5'd1;
        id_ex_rs2 = 5'd2;
        id_ex_rd = 5'd3;
        forward_a = 2'b00;
        forward_b = 2'b00;
        #10;
        $display("ADD      : alu_result=%0d rd=%0d reg_write=%b",
                 ex_mem_alu_result, ex_mem_rd, ex_mem_reg_write);

        id_ex_pc = 32'd4;
        id_ex_pc4 = 32'd8;
        id_ex_rdata1 = 32'd50;
        id_ex_rdata2 = 32'd15;
        id_ex_alu_control = 4'b0001;
        id_ex_alu_source = 1'b0;
        id_ex_rd = 5'd4;
        #10;
        $display("SUB      : alu_result=%0d rd=%0d",
                 ex_mem_alu_result, ex_mem_rd);

        id_ex_pc = 32'd8;
        id_ex_pc4 = 32'd12;
        id_ex_rdata1 = 32'd10;
        id_ex_rdata2 = 32'd0;
        id_ex_imm = 32'd5;
        id_ex_alu_control = 4'b0000;
        id_ex_alu_source = 1'b1;
        id_ex_rd = 5'd5;
        #10;
        $display("ADDI     : alu_result=%0d rd=%0d",
                 ex_mem_alu_result, ex_mem_rd);

        id_ex_pc = 32'd12;
        id_ex_pc4 = 32'd16;
        id_ex_rdata1 = 32'd10;
        id_ex_rdata2 = 32'd20;
        ex_mem_forward_data = 32'd100;
        wb_forward_data = 32'd200;
        forward_a = 2'b10;
        forward_b = 2'b00;
        id_ex_alu_control = 4'b0000;
        id_ex_alu_source = 1'b0;
        id_ex_rd = 5'd6;
        #10;
        $display("FWD A EX : alu_result=%0d expected=120",
                 ex_mem_alu_result);

        id_ex_pc = 32'd16;
        id_ex_pc4 = 32'd20;
        id_ex_rdata1 = 32'd10;
        id_ex_rdata2 = 32'd20;
        ex_mem_forward_data = 32'd100;
        wb_forward_data = 32'd200;
        forward_a = 2'b00;
        forward_b = 2'b01;
        id_ex_alu_control = 4'b0000;
        id_ex_alu_source = 1'b0;
        id_ex_rd = 5'd7;
        #10;
        $display("FWD B WB : alu_result=%0d expected=210",
                 ex_mem_alu_result);

        id_ex_pc = 32'd20;
        id_ex_pc4 = 32'd24;
        id_ex_rdata1 = 32'd30;
        id_ex_rdata2 = 32'd30;
        id_ex_imm = 32'd16;
        id_ex_alu_control = 4'b0001;
        id_ex_alu_source = 1'b0;
        id_ex_branch = 1'b1;
        id_ex_jump = 1'b0;
        id_ex_jalr = 1'b0;
        id_ex_f3 = 3'b000;
        forward_a = 2'b00;
        forward_b = 2'b00;
        id_ex_rd = 5'd0;
        id_ex_reg_write = 1'b0;
        #10;
        $display("BEQ TAKEN: ex_pc_src=%b target=%0d",
                 ex_pc_src, ex_pc_target);

        id_ex_pc = 32'd24;
        id_ex_pc4 = 32'd28;
        id_ex_rdata1 = 32'd30;
        id_ex_rdata2 = 32'd40;
        id_ex_imm = 32'd16;
        id_ex_alu_control = 4'b0001;
        id_ex_branch = 1'b1;
        id_ex_f3 = 3'b000;
        #10;
        $display("BEQ NOT  : ex_pc_src=%b target=%0d",
                 ex_pc_src, ex_pc_target);

        id_ex_pc = 32'd28;
        id_ex_pc4 = 32'd32;
        id_ex_imm = 32'd20;
        id_ex_branch = 1'b0;
        id_ex_jump = 1'b1;
        id_ex_jalr = 1'b0;
        id_ex_reg_write = 1'b1;
        id_ex_write_back_source = 2'b10;
        id_ex_rd = 5'd1;
        #10;
        $display("JAL      : ex_pc_src=%b target=%0d pc4=%0d rd=%0d wb_src=%b",
                 ex_pc_src, ex_pc_target, ex_mem_pc4, ex_mem_rd,
                 ex_mem_write_back_source);

        id_ex_pc = 32'd40;
        id_ex_pc4 = 32'd44;
        id_ex_rdata1 = 32'd100;
        id_ex_imm = 32'd12;
        id_ex_branch = 1'b0;
        id_ex_jump = 1'b0;
        id_ex_jalr = 1'b1;
        id_ex_reg_write = 1'b1;
        id_ex_write_back_source = 2'b10;
        id_ex_rd = 5'd2;
        forward_a = 2'b00;
        #10;
        $display("JALR     : ex_pc_src=%b target=%0d pc4=%0d rd=%0d wb_src=%b",
                 ex_pc_src, ex_pc_target, ex_mem_pc4, ex_mem_rd,
                 ex_mem_write_back_source);

        id_ex_pc = 32'd44;
        id_ex_pc4 = 32'd48;
        id_ex_rdata1 = 32'd0;
        id_ex_rdata2 = 32'd0;
        id_ex_imm = 32'h12345000;
        id_ex_alu_control = 4'b0000;
        id_ex_alu_source = 1'b1;
        id_ex_op = 7'b0110111;
        id_ex_branch = 1'b0;
        id_ex_jump = 1'b0;
        id_ex_jalr = 1'b0;
        id_ex_reg_write = 1'b1;
        id_ex_write_back_source = 2'b00;
        id_ex_rd = 5'd10;
        #10;
        $display("LUI      : alu_result=%h expected=12345000",
                 ex_mem_alu_result);

        id_ex_pc = 32'd100;
        id_ex_pc4 = 32'd104;
        id_ex_imm = 32'h00001000;
        id_ex_op = 7'b0010111;
        id_ex_alu_source = 1'b1;
        id_ex_alu_control = 4'b0000;
        id_ex_rd = 5'd11;
        #10;
        $display("AUIPC    : alu_result=%0d expected=%0d",
                 ex_mem_alu_result, 32'd100 + 32'h00001000);

        #20;
        $finish;
    end

endmodule

sim/ex_stage_wave.vcd
$date
	Sun Jun 14 23:11:41 2026
$end
$version
	Icarus Verilog
$end
$timescale
	1ps
$end
$scope module tb_ex_stage $end
$var wire 32 ! ex_pc_target [31:0] $end
$var wire 1 " ex_pc_src $end
$var wire 2 # ex_mem_write_back_source [1:0] $end
$var wire 1 $ ex_mem_reg_write $end
$var wire 32 % ex_mem_rdata2 [31:0] $end
$var wire 5 & ex_mem_rd [4:0] $end
$var wire 32 ' ex_mem_pc4 [31:0] $end
$var wire 1 ( ex_mem_mem_write $end
$var wire 32 ) ex_mem_alu_result [31:0] $end
$var reg 1 * clk $end
$var reg 32 + ex_mem_forward_data [31:0] $end
$var reg 2 , forward_a [1:0] $end
$var reg 2 - forward_b [1:0] $end
$var reg 4 . id_ex_alu_control [3:0] $end
$var reg 1 / id_ex_alu_source $end
$var reg 1 0 id_ex_branch $end
$var reg 3 1 id_ex_f3 [2:0] $end
$var reg 7 2 id_ex_f7 [6:0] $end
$var reg 32 3 id_ex_imm [31:0] $end
$var reg 1 4 id_ex_jalr $end
$var reg 1 5 id_ex_jump $end
$var reg 1 6 id_ex_mem_write $end
$var reg 7 7 id_ex_op [6:0] $end
$var reg 32 8 id_ex_pc [31:0] $end
$var reg 32 9 id_ex_pc4 [31:0] $end
$var reg 5 : id_ex_rd [4:0] $end
$var reg 32 ; id_ex_rdata1 [31:0] $end
$var reg 32 < id_ex_rdata2 [31:0] $end
$var reg 1 = id_ex_reg_write $end
$var reg 5 > id_ex_rs1 [4:0] $end
$var reg 5 ? id_ex_rs2 [4:0] $end
$var reg 2 @ id_ex_write_back_source [1:0] $end
$var reg 1 A rst_n $end
$var reg 32 B wb_forward_data [31:0] $end
$scope module dut $end
$var wire 1 C branch_taken $end
$var wire 1 * clk $end
$var wire 32 D ex_mem_forward_data [31:0] $end
$var wire 1 " ex_pc_src $end
$var wire 2 E forward_a [1:0] $end
$var wire 2 F forward_b [1:0] $end
$var wire 4 G id_ex_alu_control [3:0] $end
$var wire 1 / id_ex_alu_source $end
$var wire 1 0 id_ex_branch $end
$var wire 3 H id_ex_f3 [2:0] $end
$var wire 7 I id_ex_f7 [6:0] $end
$var wire 32 J id_ex_imm [31:0] $end
$var wire 1 4 id_ex_jalr $end
$var wire 1 5 id_ex_jump $end
$var wire 1 6 id_ex_mem_write $end
$var wire 7 K id_ex_op [6:0] $end
$var wire 32 L id_ex_pc [31:0] $end
$var wire 32 M id_ex_pc4 [31:0] $end
$var wire 5 N id_ex_rd [4:0] $end
$var wire 32 O id_ex_rdata1 [31:0] $end
$var wire 32 P id_ex_rdata2 [31:0] $end
$var wire 1 = id_ex_reg_write $end
$var wire 5 Q id_ex_rs1 [4:0] $end
$var wire 5 R id_ex_rs2 [4:0] $end
$var wire 2 S id_ex_write_back_source [1:0] $end
$var wire 1 A rst_n $end
$var wire 32 T wb_forward_data [31:0] $end
$var wire 1 U zero $end
$var wire 1 V less_than_u $end
$var wire 1 W less_than $end
$var wire 1 X is_lui $end
$var wire 1 Y is_auipc $end
$var wire 32 Z ex_pc_target [31:0] $end
$var wire 32 [ alu_src2 [31:0] $end
$var wire 32 \ alu_src1 [31:0] $end
$var wire 32 ] alu_result [31:0] $end
$var reg 32 ^ ex_mem_alu_result [31:0] $end
$var reg 1 ( ex_mem_mem_write $end
$var reg 32 _ ex_mem_pc4 [31:0] $end
$var reg 5 ` ex_mem_rd [4:0] $end
$var reg 32 a ex_mem_rdata2 [31:0] $end
$var reg 1 $ ex_mem_reg_write $end
$var reg 2 b ex_mem_write_back_source [1:0] $end
$var reg 32 c forwarded_rs1 [31:0] $end
$var reg 32 d forwarded_rs2 [31:0] $end
$scope module ALU $end
$var wire 4 e alu_control [3:0] $end
$var wire 32 f src1 [31:0] $end
$var wire 32 g src2 [31:0] $end
$var wire 1 U zero $end
$var wire 1 V less_than_u $end
$var wire 1 W less_than $end
$var reg 32 h alu_result [31:0] $end
$upscope $end
$upscope $end
$upscope $end
$enddefinitions $end
$comment Show the parameter values. $end
$dumpall
$end
#0
$dumpvars
b0 h
b0 g
b0 f
b0 e
b0 d
b0 c
bx b
bx a
bx `
bx _
bx ^
b0 ]
b0 \
b0 [
b0 Z
0Y
0X
0W
0V
1U
b0 T
b0 S
b0 R
b0 Q
b0 P
b0 O
b0 N
b0 M
b0 L
b0 K
b0 J
b0 I
b0 H
b0 G
b0 F
b0 E
b0 D
0C
b0 B
0A
b0 @
b0 ?
b0 >
0=
b0 <
b0 ;
b0 :
b0 9
b0 8
b0 7
06
05
04
b0 3
b0 2
b0 1
00
0/
b0 .
b0 -
b0 ,
b0 +
0*
bx )
x(
bx '
bx &
bx %
x$
bx #
0"
b0 !
$end
#5000
b0 '
b0 _
b0 &
b0 `
0$
0(
b0 #
b0 b
b0 %
b0 a
b0 )
b0 ^
1*
#10000
0*
#15000
1*
#20000
0U
b11110 ]
b11110 h
b1010 \
b1010 f
1W
1V
b10100 [
b10100 g
b10100 d
b1010 c
0*
b11 :
b11 N
b10 ?
b10 R
b1 >
b1 Q
b110011 7
b110011 K
1=
b10100 <
b10100 P
b1010 ;
b1010 O
b100 9
b100 M
1A
#25000
b100 '
b100 _
b11 &
b11 `
1$
b10100 %
b10100 a
b11110 )
b11110 ^
1*
#30000
0W
0V
b110010 \
b110010 f
b1111 [
b1111 g
b100 !
b100 Z
b100011 ]
b100011 h
b1111 d
b110010 c
0*
b100 :
b100 N
b1 .
b1 G
b1 e
b1111 <
b1111 P
b110010 ;
b110010 O
b1000 9
b1000 M
b100 8
b100 L
#35000
b1000 '
b1000 _
b100 &
b100 `
b1111 %
b1111 a
b100011 )
b100011 ^
1*
#40000
b1010 \
b1010 f
b1101 !
b1101 Z
b101 [
b101 g
b1111 ]
b1111 h
b0 d
b1010 c
0*
b101 :
b101 N
1/
b0 .
b0 G
b0 e
b101 3
b101 J
b0 <
b0 P
b1010 ;
b1010 O
b1100 9
b1100 M
b1000 8
b1000 L
#45000
b1100 '
b1100 _
b101 &
b101 `
b0 %
b0 a
b1111 )
b1111 ^
1*
#50000
b1100100 \
b1100100 f
b1111000 ]
b1111000 h
b10001 !
b10001 Z
0W
0V
b10100 [
b10100 g
b1100100 c
b10100 d
0*
b110 :
b110 N
0/
b10 ,
b10 E
b11001000 B
b11001000 T
b1100100 +
b1100100 D
b10100 <
b10100 P
b10000 9
b10000 M
b1100 8
b1100 L
#55000
b10000 '
b10000 _
b110 &
b110 `
b10100 %
b10100 a
b1111000 )
b1111000 ^
1*
#60000
b11010010 ]
b11010010 h
b1010 \
b1010 f
1W
1V
b11001000 [
b11001000 g
b10101 !
b10101 Z
b11001000 d
b1010 c
0*
b111 :
b111 N
b1 -
b1 F
b0 ,
b0 E
b10100 9
b10100 M
b10000 8
b10000 L
#65000
b10100 '
b10100 _
b111 &
b111 `
b11001000 %
b11001000 a
b11010010 )
b11010010 ^
1*
#70000
1"
1C
1U
0W
0V
b11110 \
b11110 f
b11110 [
b11110 g
b100100 !
b100100 Z
b0 ]
b0 h
b11110 d
b11110 c
0*
0=
b0 :
b0 N
b0 -
b0 F
10
b1 .
b1 G
b1 e
b10000 3
b10000 J
b11110 <
b11110 P
b11110 ;
b11110 O
b11000 9
b11000 M
b10100 8
b10100 L
#75000
b11000 '
b11000 _
b0 &
b0 `
0$
b11110 %
b11110 a
b0 )
b0 ^
1*
#80000
0"
0C
0U
b11111111111111111111111111110110 ]
b11111111111111111111111111110110 h
1W
1V
b101000 [
b101000 g
b101000 !
b101000 Z
b101000 d
0*
b101000 <
b101000 P
b11100 9
b11100 M
b11000 8
b11000 L
#85000
b11100 '
b11100 _
b101000 %
b101000 a
b11111111111111111111111111110110 )
b11111111111111111111111111110110 ^
1*
#90000
1"
b110000 !
b110000 Z
0*
b1 :
b1 N
b10 @
b10 S
1=
15
00
b10100 3
b10100 J
b100000 9
b100000 M
b11100 8
b11100 L
#95000
b100000 '
b100000 _
b1 &
b1 `
1$
b10 #
b10 b
1*
#100000
b111100 ]
b111100 h
0W
0V
b1100100 \
b1100100 f
b1100100 c
b1110000 !
b1110000 Z
0*
b10 :
b10 N
14
05
b1100 3
b1100 J
b1100100 ;
b1100100 O
b101100 9
b101100 M
b101000 8
b101000 L
#105000
b101100 '
b101100 _
b10 &
b10 `
b111100 )
b111100 ^
1*
#110000
0"
b10010001101000101000000101100 !
b10010001101000101000000101100 Z
b0 \
b0 f
1W
1V
b10010001101000101000000000000 [
b10010001101000101000000000000 g
b10010001101000101000000000000 ]
b10010001101000101000000000000 h
b0 d
b0 c
0*
b1010 :
b1010 N
b0 @
b0 S
04
1X
b110111 7
b110111 K
1/
b0 .
b0 G
b0 e
b10010001101000101000000000000 3
b10010001101000101000000000000 J
b0 <
b0 P
b0 ;
b0 O
b110000 9
b110000 M
b101100 8
b101100 L
#115000
b110000 '
b110000 _
b1010 &
b1010 `
b0 #
b0 b
b0 %
b0 a
b10010001101000101000000000000 )
b10010001101000101000000000000 ^
1*
#120000
b1000001100100 ]
b1000001100100 h
b1000001100100 !
b1000001100100 Z
b1100100 \
b1100100 f
b1000000000000 [
b1000000000000 g
0*
b1011 :
b1011 N
0X
1Y
b10111 7
b10111 K
b1000000000000 3
b1000000000000 J
b1101000 9
b1101000 M
b1100100 8
b1100100 L
#125000
b1101000 '
b1101000 _
b1011 &
b1011 `
b1000001100100 )
b1000001100100 ^
1*
