rtl/forwarding_unit.v
module forwarding_unit (
    // Source registers of instruction currently in EX stage
    input  wire [4:0] id_ex_rs1,
    input  wire [4:0] id_ex_rs2,

    // Destination register of instruction currently in MEM stage
    input  wire [4:0] ex_mem_rd,
    input  wire       ex_mem_reg_write,

    // Destination register of instruction currently in WB stage
    input  wire [4:0] mem_wb_rd,
    input  wire       mem_wb_reg_write,

    // Forwarding select outputs
    // 2'b00 -> use original id_ex_rdata
    // 2'b10 -> forward from EX/MEM stage
    // 2'b01 -> forward from MEM/WB stage
    output reg  [1:0] forward_a,
    output reg  [1:0] forward_b
);

always @(*) begin
    // Default: no forwarding
    forward_a = 2'b00;
    forward_b = 2'b00;

    // =========================
    // Forward for ALU src1 (rs1)
    // =========================
    // Highest priority: EX/MEM
    if (ex_mem_reg_write &&
        (ex_mem_rd != 5'b00000) &&
        (ex_mem_rd == id_ex_rs1)) begin
        forward_a = 2'b10;
    end
    // Next priority: MEM/WB
    else if (mem_wb_reg_write &&
             (mem_wb_rd != 5'b00000) &&
             (mem_wb_rd == id_ex_rs1)) begin
        forward_a = 2'b01;
    end

    // =========================
    // Forward for ALU src2 (rs2)
    // =========================
    // Highest priority: EX/MEM
    if (ex_mem_reg_write &&
        (ex_mem_rd != 5'b00000) &&
        (ex_mem_rd == id_ex_rs2)) begin
        forward_b = 2'b10;
    end
    // Next priority: MEM/WB
    else if (mem_wb_reg_write &&
             (mem_wb_rd != 5'b00000) &&
             (mem_wb_rd == id_ex_rs2)) begin
        forward_b = 2'b01;
    end
end

endmodule

tb/tb_forwarding_unit.v
`timescale 1ns/1ps
`include "../rtl/forwarding_unit.v"

module tb_forwarding_unit;

    reg  [4:0] id_ex_rs1;
    reg  [4:0] id_ex_rs2;

    reg  [4:0] ex_mem_rd;
    reg        ex_mem_reg_write;

    reg  [4:0] mem_wb_rd;
    reg        mem_wb_reg_write;

    wire [1:0] forward_a;
    wire [1:0] forward_b;

    forwarding_unit dut (
        .id_ex_rs1        (id_ex_rs1),
        .id_ex_rs2        (id_ex_rs2),
        .ex_mem_rd        (ex_mem_rd),
        .ex_mem_reg_write (ex_mem_reg_write),
        .mem_wb_rd        (mem_wb_rd),
        .mem_wb_reg_write (mem_wb_reg_write),
        .forward_a        (forward_a),
        .forward_b        (forward_b)
    );

    initial begin
        $dumpfile("../sim/forwarding_unit_wave.vcd");
        $dumpvars(0, tb_forwarding_unit);

        id_ex_rs1 = 5'd1;
        id_ex_rs2 = 5'd2;
        ex_mem_rd = 5'd0;
        ex_mem_reg_write = 1'b0;
        mem_wb_rd = 5'd0;
        mem_wb_reg_write = 1'b0;
        #20;
        $display("NO HAZARD        : forward_a=%b forward_b=%b", forward_a, forward_b);

        id_ex_rs1 = 5'd1;
        id_ex_rs2 = 5'd2;
        ex_mem_rd = 5'd1;
        ex_mem_reg_write = 1'b1;
        mem_wb_rd = 5'd0;
        mem_wb_reg_write = 1'b0;
        #20;
        $display("EX/MEM -> RS1    : forward_a=%b forward_b=%b", forward_a, forward_b);

        id_ex_rs1 = 5'd1;
        id_ex_rs2 = 5'd2;
        ex_mem_rd = 5'd2;
        ex_mem_reg_write = 1'b1;
        mem_wb_rd = 5'd0;
        mem_wb_reg_write = 1'b0;
        #20;
        $display("EX/MEM -> RS2    : forward_a=%b forward_b=%b", forward_a, forward_b);

        id_ex_rs1 = 5'd3;
        id_ex_rs2 = 5'd4;
        ex_mem_rd = 5'd0;
        ex_mem_reg_write = 1'b0;
        mem_wb_rd = 5'd3;
        mem_wb_reg_write = 1'b1;
        #20;
        $display("MEM/WB -> RS1    : forward_a=%b forward_b=%b", forward_a, forward_b);

        id_ex_rs1 = 5'd3;
        id_ex_rs2 = 5'd4;
        ex_mem_rd = 5'd0;
        ex_mem_reg_write = 1'b0;
        mem_wb_rd = 5'd4;
        mem_wb_reg_write = 1'b1;
        #20;
        $display("MEM/WB -> RS2    : forward_a=%b forward_b=%b", forward_a, forward_b);

        id_ex_rs1 = 5'd5;
        id_ex_rs2 = 5'd5;
        ex_mem_rd = 5'd5;
        ex_mem_reg_write = 1'b1;
        mem_wb_rd = 5'd0;
        mem_wb_reg_write = 1'b0;
        #20;
        $display("EX/MEM -> BOTH   : forward_a=%b forward_b=%b", forward_a, forward_b);

        id_ex_rs1 = 5'd6;
        id_ex_rs2 = 5'd7;
        ex_mem_rd = 5'd6;
        ex_mem_reg_write = 1'b1;
        mem_wb_rd = 5'd6;
        mem_wb_reg_write = 1'b1;
        #20;
        $display("PRIORITY CHECK   : forward_a=%b forward_b=%b", forward_a, forward_b);

        id_ex_rs1 = 5'd8;
        id_ex_rs2 = 5'd9;
        ex_mem_rd = 5'd0;
        ex_mem_reg_write = 1'b1;
        mem_wb_rd = 5'd0;
        mem_wb_reg_write = 1'b1;
        #20;
        $display("x0 IGNORE CHECK  : forward_a=%b forward_b=%b", forward_a, forward_b);

        #20;
        $finish;
    end

endmodule

sim/forwarding_unit_wave.vcd
$date
	Sat Jun 13 19:44:27 2026
$end
$version
	Icarus Verilog
$end
$timescale
	1ps
$end
$scope module tb_forwarding_unit $end
$var wire 2 ! forward_b [1:0] $end
$var wire 2 " forward_a [1:0] $end
$var reg 5 # ex_mem_rd [4:0] $end
$var reg 1 $ ex_mem_reg_write $end
$var reg 5 % id_ex_rs1 [4:0] $end
$var reg 5 & id_ex_rs2 [4:0] $end
$var reg 5 ' mem_wb_rd [4:0] $end
$var reg 1 ( mem_wb_reg_write $end
$scope module dut $end
$var wire 5 ) ex_mem_rd [4:0] $end
$var wire 1 $ ex_mem_reg_write $end
$var wire 5 * id_ex_rs1 [4:0] $end
$var wire 5 + id_ex_rs2 [4:0] $end
$var wire 5 , mem_wb_rd [4:0] $end
$var wire 1 ( mem_wb_reg_write $end
$var reg 2 - forward_a [1:0] $end
$var reg 2 . forward_b [1:0] $end
$upscope $end
$upscope $end
$enddefinitions $end
$comment Show the parameter values. $end
$dumpall
$end
#0
$dumpvars
b0 .
b0 -
b0 ,
b10 +
b1 *
b0 )
0(
b0 '
b10 &
b1 %
0$
b0 #
b0 "
b0 !
$end
#20000
b10 "
b10 -
1$
b1 #
b1 )
#40000
b10 !
b10 .
b0 "
b0 -
b10 #
b10 )
#60000
b1 "
b1 -
b0 !
b0 .
1(
b11 '
b11 ,
0$
b0 #
b0 )
b100 &
b100 +
b11 %
b11 *
#80000
b1 !
b1 .
b0 "
b0 -
b100 '
b100 ,
#100000
b10 "
b10 -
b10 !
b10 .
0(
b0 '
b0 ,
1$
b101 #
b101 )
b101 &
b101 +
b101 %
b101 *
#120000
b0 !
b0 .
b10 "
b10 -
1(
b110 '
b110 ,
b110 #
b110 )
b111 &
b111 +
b110 %
b110 *
#140000
b0 "
b0 -
b0 '
b0 ,
b0 #
b0 )
b1001 &
b1001 +
b1000 %
b1000 *
