rtl/sign_ext.v
module sign_ext (
    input  [31:0] raw_src,
    input  [2:0] imm_source,
    // OUT (immediate)
    output  [31:0] immediate  
);

reg [31:0] gathered_imm; 

always @(*) begin
    case (imm_source)
        // I type -> lw
        3'b000 : gathered_imm = {{20{raw_src[31]}}, raw_src[31:20]};
        // S type -> sw
        3'b001 : gathered_imm = {{20{raw_src[31]}}, raw_src[31:25], raw_src[11:7]};
        //B type -> beq
        3'b010 : gathered_imm = {{20{raw_src[31]}}, raw_src[7], raw_src[30:25], raw_src[11:8], 1'b0};
        //J Type -> jal
        3'b011 : gathered_imm = {{12{raw_src[31]}}, raw_src[19:12], raw_src[20], raw_src[30:21], 1'b0};
        //U Type instruction
        3'b100 : gathered_imm = {raw_src[31:12],12'b000000000000};
        //Default case : all zeroes
        default : gathered_imm = 32'b0; 
    endcase
end

    

assign immediate = gathered_imm;

endmodule

rtl/reg_file.v
module reg_file (
    //clk 
    input clk,
    //writes
    input [4:0] address1,address2,
    output reg [31:0] read_data1,read_data2,
    //writes
    input write_enable,
    input [4:0] address3,
    input [31:0] write_data
);

reg [31:0] register [31:0];

//write operation

always @(posedge clk ) begin
    if (write_enable && address3 != 5'd0) begin  // If register is x0 , ignore the write
        register[address3] <= write_data;
    end
end

//read operation
//X0 register is  hardwired to 0
always @(*) begin
    read_data1 = (address1 == 5'd0) ? 32'b0 : register[address1];
    read_data2 = (address2 == 5'd0) ? 32'b0 : register[address2];
end
    
endmodule

rtl/control.v
module control (
    input  [6:0] op,
    input  [2:0] func3,
    input  [6:0] func7,

    //OUT
    output reg [3:0] alu_control,
    output reg [2:0] imm_source,
    output reg mem_write,
    output reg  reg_write,
    //added for R type instruction
    output reg alu_source,
    output reg [1:0] write_back_source,
    //for U type 
    output reg second_add_source,
    output reg branch,
    output reg jump,
    output reg jalr
);


/////////////////////////////////
///Main decoder to compute alu_op///
////////////////////////////////////

reg [1:0] alu_op;


always @(*) begin

    // defaults values
    reg_write         = 1'b0;
    imm_source        = 3'b000;
    mem_write         = 1'b0;
    alu_op            = 2'b00;
    alu_source        = 1'b0;
    write_back_source = 2'b00;
    second_add_source = 1'b0;
    branch            = 1'b0;
    jump              = 1'b0;
    jalr              = 1'b0;

    case (op)

    //LW , I type
        7'b0000011 : begin
            reg_write = 1'b1;
            imm_source = 3'b000;
            mem_write = 1'b0;
            alu_op = 2'b00;
            alu_source = 1'b1;
            write_back_source = 2'b01; 
            branch = 1'b0;
            jump = 1'b0;
        end
    //SW , S type
        7'b0100011 : begin
            reg_write = 1'b0;
            imm_source = 3'b001;
            mem_write = 1'b1;
            alu_op = 2'b00;
            alu_source = 1'b1;
            branch = 1'b0;
            jump = 1'b0;
        end

    //R Type -> add , or , and
        7'b0110011 : begin
            reg_write = 1'b1;
            mem_write = 1'b0;
            alu_op = 2'b10;
            alu_source = 1'b0; //take reg2 instead of immediate
            write_back_source = 2'b00; // take the alu_result instead of memory value
            branch = 1'b0;
            jump = 1'b0;
        end

    //B Type -> beq
        7'b1100011 : begin
            reg_write = 1'b0;
            imm_source = 3'b010;
            alu_source = 1'b0;
            mem_write = 1'b0;
            alu_op = 2'b01;
            branch = 1'b1;
            jump = 1'b0;
            //modified while adding u type
            second_add_source = 1'b0;
        end

    //J Type -> jal
        7'b1101111 : begin
            reg_write = 1'b1;
            imm_source = 3'b011;
            mem_write = 1'b0;
            write_back_source = 2'b10; //store pc = pc+4 into a destination register
            branch = 1'b0;
            jump = 1'b1;
            //modifed while adding u type
            second_add_source = 1'b0;
        end

    //I type - ALU instructions : addi
        7'b0010011 : begin
            reg_write = 1'b1;
            imm_source = 3'b000;
            alu_source = 1'b1; // select immediate as src2 of ALU
            mem_write = 1'b0;
            alu_op = 2'b10; //R type instr
            write_back_source = 2'b00; //write back the ALU Result to the dest reg
            branch = 1'b0;
            jump = 1'b0;
        end

    // U Type instructions : lui and auipc
        7'b0110111, 7'b0010111 : begin
            imm_source = 3'b100;
            mem_write = 1'b0;
            reg_write = 1'b1;
            write_back_source = 2'b00;
            branch = 1'b0;
            jump = 1'b0;
            alu_source = 1'b1;
            alu_op = 2'b00;
            if (op == 7'b0110111)
                second_add_source = 1'b1; // LUI → immediate only
            else
                second_add_source = 1'b0; // AUIPC → PC + immediate
        end

    //JALR 

        7'b1100111 : begin
            reg_write = 1'b1;
            imm_source = 3'b000;        // I-type immediate
            mem_write = 1'b0;
            write_back_source = 2'b10;  // rd = PC + 4
            branch = 1'b0;
            jump   = 1'b0;
            // JALR signal is 1
            jalr = 1'b1;
            alu_op = 2'b00;
            alu_source = 1'b1;
            second_add_source = 1'b0;
        end

        default: begin
            reg_write = 1'b0;
            imm_source = 3'b000;
            mem_write = 1'b0;
            alu_op = 2'b00;
            alu_source = 1'b0;
            branch = 1'b0;
            jump = 1'b0;
        end
    endcase
end

////////////////////////////////////
//ALU DECODER to compute alu_control
////////////////////////////////////

always @(*) begin
    case (alu_op)
    //LW and SW , ALU has to add
        2'b00 : alu_control = 4'b0000;
    //R Type instruction , ALU Operation is dependent on func3, func7
        2'b10 : begin
            case (func3)
                // ADD and SUB have same funct3 but diff is at funct7
                3'b000 : begin
                    if ((op == 7'b0110011) && (func7 == 7'b0100000))
                        alu_control = 4'b0001;   // SUB
                    else
                        alu_control = 4'b0000;   // ADD and ADDI
                end
                //AND
                3'b111 : alu_control = 4'b0010;
                //OR instruction
                3'b110 : alu_control = 4'b0011;
                //SLTI instruction
                3'b010 : alu_control = 4'b0101;
                //SLTU Instruction
                3'b011 : alu_control = 4'b0111;
                //xor
                3'b100 : alu_control = 4'b1000;
                //SLLI instruction
                3'b001 : alu_control = 4'b1001;

                //SRLI / SRAI (and SRL / SRA) have same funct3 they are difference by funct7
                3'b101 : begin
                    if (func7 == 7'b0100000)
                        alu_control = 4'b1011;  // SRAI (arithmetic shift right)
                    else
                        alu_control = 4'b1010;  // SRLI (logical shift right)
                    end
                // ALL THE OTHERS
                default: alu_control = 4'b0000;
            endcase
        end
    //REST OF THE INSTRUCTIONS
    //B type -> beq
        //ALU Has to sub to compare reg1 , reg2
        2'b01 : begin
            //Based on func3 we can differentiate Branch instructions
            case (func3)
                3'b000 : alu_control = 4'b0001;  // BEQ
                3'b001 : alu_control = 4'b0001;  // BNE
                3'b100 : alu_control = 4'b0101;  // BLT
                3'b101 : alu_control = 4'b0101;  // BGE
                3'b110 : alu_control = 4'b0111;  // BLTU
                3'b111 : alu_control = 4'b0111;  // BGEU
                default: alu_control = 4'b0001;
            endcase
        end

        default: alu_control = 4'b0111;
    endcase
end




endmodule

rtl/id_stage.v
module id_stage (
    input  wire        clk,
    input  wire        rst_n,

    // Load-stall bubble control
    input  wire        control_mux_sel,

    // Branch flush control
    input  wire        id_ex_flush,

    input  wire [31:0] if_id_pc,
    input  wire [31:0] if_id_pc4,
    input  wire [31:0] if_id_instr,

    // From WB stage
    input  wire        wb_write_enable,
    input  wire [4:0]  wb_rd,
    input  wire [31:0] wb_wdata,

    output reg  [31:0] id_ex_pc,
    output reg  [31:0] id_ex_pc4,
    output reg  [31:0] id_ex_rdata1,
    output reg  [31:0] id_ex_rdata2,
    output reg  [31:0] id_ex_imm,

    output reg  [3:0]  id_ex_alu_control,
    output reg         id_ex_alu_source,
    output reg  [1:0]  id_ex_write_back_source,
    output reg         id_ex_mem_write,
    output reg         id_ex_reg_write,

    output reg         id_ex_branch,
    output reg         id_ex_jump,
    output reg         id_ex_jalr,

    output reg  [6:0]  id_ex_op,
    output reg  [2:0]  id_ex_f3,
    output reg  [6:0]  id_ex_f7,
    output reg  [4:0]  id_ex_rs1,
    output reg  [4:0]  id_ex_rs2,
    output reg  [4:0]  id_ex_rd
);

    wire [6:0] op    = if_id_instr[6:0];
    wire [2:0] func3 = if_id_instr[14:12];
    wire [6:0] func7 = if_id_instr[31:25];
    wire [4:0] rs1   = if_id_instr[19:15];
    wire [4:0] rs2   = if_id_instr[24:20];
    wire [4:0] rd    = if_id_instr[11:7];

    wire [31:0] rf_rdata1;
    wire [31:0] rf_rdata2;
    wire [31:0] imm;

    wire [3:0] alu_control;
    wire [2:0] imm_source;
    wire       mem_write;
    wire       reg_write;
    wire       alu_source;
    wire [1:0] write_back_source;
    wire       second_add_source;
    wire       branch;
    wire       jump;
    wire       jalr;

    control CTRL (
        .op(op),
        .func3(func3),
        .func7(func7),

        .alu_control(alu_control),
        .imm_source(imm_source),
        .mem_write(mem_write),
        .reg_write(reg_write),
        .alu_source(alu_source),
        .write_back_source(write_back_source),
        .second_add_source(second_add_source),
        .branch(branch),
        .jump(jump),
        .jalr(jalr)
    );

    reg_file RF (
        .clk(clk),

        .address1(rs1),
        .address2(rs2),
        .read_data1(rf_rdata1),
        .read_data2(rf_rdata2),

        .write_enable(wb_write_enable),
        .address3(wb_rd),
        .write_data(wb_wdata)
    );

    sign_ext SE (
        .raw_src(if_id_instr),
        .imm_source(imm_source),
        .immediate(imm)
    );

    // ID/EX pipeline register
    always @(posedge clk) begin
        if (!rst_n) begin
            id_ex_pc                <= 32'b0;
            id_ex_pc4               <= 32'b0;
            id_ex_rdata1            <= 32'b0;
            id_ex_rdata2            <= 32'b0;
            id_ex_imm               <= 32'b0;

            id_ex_alu_control       <= 4'b0;
            id_ex_alu_source        <= 1'b0;
            id_ex_write_back_source <= 2'b0;
            id_ex_mem_write         <= 1'b0;
            id_ex_reg_write         <= 1'b0;

            id_ex_branch            <= 1'b0;
            id_ex_jump              <= 1'b0;
            id_ex_jalr              <= 1'b0;

            id_ex_op                <= 7'b0;
            id_ex_f3                <= 3'b0;
            id_ex_f7                <= 7'b0;
            id_ex_rs1               <= 5'b0;
            id_ex_rs2               <= 5'b0;
            id_ex_rd                <= 5'b0;
        end

        else if (id_ex_flush || control_mux_sel) begin
            id_ex_pc                <= 32'b0;
            id_ex_pc4               <= 32'b0;
            id_ex_rdata1            <= 32'b0;
            id_ex_rdata2            <= 32'b0;
            id_ex_imm               <= 32'b0;

            id_ex_alu_control       <= 4'b0;
            id_ex_alu_source        <= 1'b0;
            id_ex_write_back_source <= 2'b0;
            id_ex_mem_write         <= 1'b0;
            id_ex_reg_write         <= 1'b0;

            id_ex_branch            <= 1'b0;
            id_ex_jump              <= 1'b0;
            id_ex_jalr              <= 1'b0;

            id_ex_op                <= 7'b0;
            id_ex_f3                <= 3'b0;
            id_ex_f7                <= 7'b0;
            id_ex_rs1               <= 5'b0;
            id_ex_rs2               <= 5'b0;
            id_ex_rd                <= 5'b0;
        end

        else begin
            id_ex_pc     <= if_id_pc;
            id_ex_pc4    <= if_id_pc4;
            id_ex_rdata1 <= rf_rdata1;
            id_ex_rdata2 <= rf_rdata2;
            id_ex_imm    <= imm;

            id_ex_alu_control       <= alu_control;
            id_ex_alu_source        <= alu_source;
            id_ex_write_back_source <= write_back_source;
            id_ex_mem_write         <= mem_write;
            id_ex_reg_write         <= reg_write;

            id_ex_branch            <= branch;
            id_ex_jump              <= jump;
            id_ex_jalr              <= jalr;

            id_ex_op                <= op;
            id_ex_f3                <= func3;
            id_ex_f7                <= func7;
            id_ex_rs1               <= rs1;
            id_ex_rs2               <= rs2;
            id_ex_rd                <= rd;
        end
    end

endmodule

tb/tb_id_stage.v
`timescale 1ns/1ps

`include "../rtl/control.v"
`include "../rtl/sign_ext.v"
`include "../rtl/reg_file.v"
`include "../rtl/id_stage.v"

module tb_id_stage;

    reg         clk;
    reg         rst_n;

    reg         control_mux_sel;
    reg         id_ex_flush;

    reg  [31:0] if_id_pc;
    reg  [31:0] if_id_pc4;
    reg  [31:0] if_id_instr;

    reg         wb_write_enable;
    reg  [4:0]  wb_rd;
    reg  [31:0] wb_wdata;

    wire [31:0] id_ex_pc;
    wire [31:0] id_ex_pc4;
    wire [31:0] id_ex_rdata1;
    wire [31:0] id_ex_rdata2;
    wire [31:0] id_ex_imm;

    wire [3:0]  id_ex_alu_control;
    wire        id_ex_alu_source;
    wire [1:0]  id_ex_write_back_source;
    wire        id_ex_mem_write;
    wire        id_ex_reg_write;

    wire        id_ex_branch;
    wire        id_ex_jump;
    wire        id_ex_jalr;

    wire [6:0]  id_ex_op;
    wire [2:0]  id_ex_f3;
    wire [6:0]  id_ex_f7;
    wire [4:0]  id_ex_rs1;
    wire [4:0]  id_ex_rs2;
    wire [4:0]  id_ex_rd;

    id_stage dut (
        .clk                     (clk),
        .rst_n                   (rst_n),

        .control_mux_sel         (control_mux_sel),
        .id_ex_flush             (id_ex_flush),

        .if_id_pc                (if_id_pc),
        .if_id_pc4               (if_id_pc4),
        .if_id_instr             (if_id_instr),

        .wb_write_enable         (wb_write_enable),
        .wb_rd                   (wb_rd),
        .wb_wdata                (wb_wdata),

        .id_ex_pc                (id_ex_pc),
        .id_ex_pc4               (id_ex_pc4),
        .id_ex_rdata1            (id_ex_rdata1),
        .id_ex_rdata2            (id_ex_rdata2),
        .id_ex_imm               (id_ex_imm),

        .id_ex_alu_control       (id_ex_alu_control),
        .id_ex_alu_source        (id_ex_alu_source),
        .id_ex_write_back_source (id_ex_write_back_source),
        .id_ex_mem_write         (id_ex_mem_write),
        .id_ex_reg_write         (id_ex_reg_write),

        .id_ex_branch            (id_ex_branch),
        .id_ex_jump              (id_ex_jump),
        .id_ex_jalr              (id_ex_jalr),

        .id_ex_op                (id_ex_op),
        .id_ex_f3                (id_ex_f3),
        .id_ex_f7                (id_ex_f7),
        .id_ex_rs1               (id_ex_rs1),
        .id_ex_rs2               (id_ex_rs2),
        .id_ex_rd                (id_ex_rd)
    );

    always #5 clk = ~clk;

    initial begin
        $dumpfile("../sim/id_stage_wave.vcd");
        $dumpvars(0, tb_id_stage);

        clk = 0;
        rst_n = 0;

        control_mux_sel = 0;
        id_ex_flush = 0;

        if_id_pc = 0;
        if_id_pc4 = 4;
        if_id_instr = 32'b0;

        wb_write_enable = 0;
        wb_rd = 0;
        wb_wdata = 0;

        #20;
        rst_n = 1;

        wb_rd = 5'd1;
        wb_wdata = 32'd10;
        wb_write_enable = 1;
        #10;
        wb_write_enable = 0;

        wb_rd = 5'd2;
        wb_wdata = 32'd20;
        wb_write_enable = 1;
        #10;
        wb_write_enable = 0;

        if_id_pc = 32'd0;
        if_id_pc4 = 32'd4;
        if_id_instr = 32'h002081B3;   
        #10;
        $display("ADD  : rs1=%0d rs2=%0d rd=%0d rdata1=%0d rdata2=%0d alu_ctrl=%b reg_write=%b",
                 id_ex_rs1, id_ex_rs2, id_ex_rd,
                 id_ex_rdata1, id_ex_rdata2,
                 id_ex_alu_control, id_ex_reg_write);

        if_id_pc = 32'd4;
        if_id_pc4 = 32'd8;
        if_id_instr = 32'h00518213;
        #10;
        $display("ADDI : rs1=%0d rd=%0d rdata1=%0d imm=%0d alu_src=%b reg_write=%b",
                 id_ex_rs1, id_ex_rd,
                 id_ex_rdata1, id_ex_imm,
                 id_ex_alu_source, id_ex_reg_write);

        if_id_pc = 32'd8;
        if_id_pc4 = 32'd12;
        if_id_instr = 32'h0041A283;
        #10;
        $display("LW   : rs1=%0d rd=%0d imm=%0d alu_src=%b wb_src=%b reg_write=%b mem_write=%b",
                 id_ex_rs1, id_ex_rd, id_ex_imm,
                 id_ex_alu_source, id_ex_write_back_source,
                 id_ex_reg_write, id_ex_mem_write);

        if_id_pc = 32'd12;
        if_id_pc4 = 32'd16;
        if_id_instr = 32'h0051A223;
        #10;
        $display("SW   : rs1=%0d rs2=%0d imm=%0d alu_src=%b reg_write=%b mem_write=%b",
                 id_ex_rs1, id_ex_rs2, id_ex_imm,
                 id_ex_alu_source, id_ex_reg_write, id_ex_mem_write);

        if_id_pc = 32'd16;
        if_id_pc4 = 32'd20;
        if_id_instr = 32'h00208463;
        #10;
        $display("BEQ  : rs1=%0d rs2=%0d imm=%0d branch=%b reg_write=%b mem_write=%b",
                 id_ex_rs1, id_ex_rs2, id_ex_imm,
                 id_ex_branch, id_ex_reg_write, id_ex_mem_write);

        control_mux_sel = 1;
        if_id_instr = 32'h002081B3;
        #10;
        $display("STALL BUBBLE : reg_write=%b mem_write=%b branch=%b jump=%b jalr=%b rd=%0d",
                 id_ex_reg_write, id_ex_mem_write,
                 id_ex_branch, id_ex_jump, id_ex_jalr, id_ex_rd);

        control_mux_sel = 0;

        id_ex_flush = 1;
        if_id_instr = 32'h00518213;
        #10;
        $display("BRANCH FLUSH : reg_write=%b mem_write=%b branch=%b jump=%b jalr=%b rd=%0d",
                 id_ex_reg_write, id_ex_mem_write,
                 id_ex_branch, id_ex_jump, id_ex_jalr, id_ex_rd);

        id_ex_flush = 0;

        if_id_pc = 32'd24;
        if_id_pc4 = 32'd28;
        if_id_instr = 32'h008000EF;
        #10;
        $display("JAL  : rd=%0d imm=%0d jump=%b wb_src=%b reg_write=%b",
                 id_ex_rd, id_ex_imm,
                 id_ex_jump, id_ex_write_back_source, id_ex_reg_write);

        if_id_pc = 32'd28;
        if_id_pc4 = 32'd32;
        if_id_instr = 32'h000080E7;
        #10;
        $display("JALR : rs1=%0d rd=%0d imm=%0d jalr=%b wb_src=%b reg_write=%b",
                 id_ex_rs1, id_ex_rd, id_ex_imm,
                 id_ex_jalr, id_ex_write_back_source, id_ex_reg_write);

        #20;
        $finish;
    end

endmodule

sim/id_stage_wave.vcd
$date
	Sun Jun 14 23:02:13 2026
$end
$version
	Icarus Verilog
$end
$timescale
	1ps
$end
$scope module tb_id_stage $end
$var wire 2 ! id_ex_write_back_source [1:0] $end
$var wire 5 " id_ex_rs2 [4:0] $end
$var wire 5 # id_ex_rs1 [4:0] $end
$var wire 1 $ id_ex_reg_write $end
$var wire 32 % id_ex_rdata2 [31:0] $end
$var wire 32 & id_ex_rdata1 [31:0] $end
$var wire 5 ' id_ex_rd [4:0] $end
$var wire 32 ( id_ex_pc4 [31:0] $end
$var wire 32 ) id_ex_pc [31:0] $end
$var wire 7 * id_ex_op [6:0] $end
$var wire 1 + id_ex_mem_write $end
$var wire 1 , id_ex_jump $end
$var wire 1 - id_ex_jalr $end
$var wire 32 . id_ex_imm [31:0] $end
$var wire 7 / id_ex_f7 [6:0] $end
$var wire 3 0 id_ex_f3 [2:0] $end
$var wire 1 1 id_ex_branch $end
$var wire 1 2 id_ex_alu_source $end
$var wire 4 3 id_ex_alu_control [3:0] $end
$var reg 1 4 clk $end
$var reg 1 5 control_mux_sel $end
$var reg 1 6 id_ex_flush $end
$var reg 32 7 if_id_instr [31:0] $end
$var reg 32 8 if_id_pc [31:0] $end
$var reg 32 9 if_id_pc4 [31:0] $end
$var reg 1 : rst_n $end
$var reg 5 ; wb_rd [4:0] $end
$var reg 32 < wb_wdata [31:0] $end
$var reg 1 = wb_write_enable $end
$scope module dut $end
$var wire 1 4 clk $end
$var wire 1 5 control_mux_sel $end
$var wire 1 6 id_ex_flush $end
$var wire 32 > if_id_instr [31:0] $end
$var wire 32 ? if_id_pc [31:0] $end
$var wire 32 @ if_id_pc4 [31:0] $end
$var wire 1 : rst_n $end
$var wire 5 A wb_rd [4:0] $end
$var wire 32 B wb_wdata [31:0] $end
$var wire 1 = wb_write_enable $end
$var wire 2 C write_back_source [1:0] $end
$var wire 1 D second_add_source $end
$var wire 5 E rs2 [4:0] $end
$var wire 5 F rs1 [4:0] $end
$var wire 32 G rf_rdata2 [31:0] $end
$var wire 32 H rf_rdata1 [31:0] $end
$var wire 1 I reg_write $end
$var wire 5 J rd [4:0] $end
$var wire 7 K op [6:0] $end
$var wire 1 L mem_write $end
$var wire 1 M jump $end
$var wire 1 N jalr $end
$var wire 3 O imm_source [2:0] $end
$var wire 32 P imm [31:0] $end
$var wire 7 Q func7 [6:0] $end
$var wire 3 R func3 [2:0] $end
$var wire 1 S branch $end
$var wire 1 T alu_source $end
$var wire 4 U alu_control [3:0] $end
$var reg 4 V id_ex_alu_control [3:0] $end
$var reg 1 2 id_ex_alu_source $end
$var reg 1 1 id_ex_branch $end
$var reg 3 W id_ex_f3 [2:0] $end
$var reg 7 X id_ex_f7 [6:0] $end
$var reg 32 Y id_ex_imm [31:0] $end
$var reg 1 - id_ex_jalr $end
$var reg 1 , id_ex_jump $end
$var reg 1 + id_ex_mem_write $end
$var reg 7 Z id_ex_op [6:0] $end
$var reg 32 [ id_ex_pc [31:0] $end
$var reg 32 \ id_ex_pc4 [31:0] $end
$var reg 5 ] id_ex_rd [4:0] $end
$var reg 32 ^ id_ex_rdata1 [31:0] $end
$var reg 32 _ id_ex_rdata2 [31:0] $end
$var reg 1 $ id_ex_reg_write $end
$var reg 5 ` id_ex_rs1 [4:0] $end
$var reg 5 a id_ex_rs2 [4:0] $end
$var reg 2 b id_ex_write_back_source [1:0] $end
$scope module CTRL $end
$var wire 3 c func3 [2:0] $end
$var wire 7 d func7 [6:0] $end
$var wire 7 e op [6:0] $end
$var reg 4 f alu_control [3:0] $end
$var reg 2 g alu_op [1:0] $end
$var reg 1 T alu_source $end
$var reg 1 S branch $end
$var reg 3 h imm_source [2:0] $end
$var reg 1 N jalr $end
$var reg 1 M jump $end
$var reg 1 L mem_write $end
$var reg 1 I reg_write $end
$var reg 1 D second_add_source $end
$var reg 2 i write_back_source [1:0] $end
$upscope $end
$scope module RF $end
$var wire 5 j address1 [4:0] $end
$var wire 5 k address2 [4:0] $end
$var wire 5 l address3 [4:0] $end
$var wire 1 4 clk $end
$var wire 32 m write_data [31:0] $end
$var wire 1 = write_enable $end
$var reg 32 n read_data1 [31:0] $end
$var reg 32 o read_data2 [31:0] $end
$upscope $end
$scope module SE $end
$var wire 3 p imm_source [2:0] $end
$var wire 32 q immediate [31:0] $end
$var wire 32 r raw_src [31:0] $end
$var reg 32 s gathered_imm [31:0] $end
$upscope $end
$upscope $end
$upscope $end
$enddefinitions $end
$comment Show the parameter values. $end
$dumpall
$end
#0
$dumpvars
b0 s
b0 r
b0 q
b0 p
b0 o
b0 n
b0 m
b0 l
b0 k
b0 j
b0 i
b0 h
b0 g
b0 f
b0 e
b0 d
b0 c
bx b
bx a
bx `
bx _
bx ^
bx ]
bx \
bx [
bx Z
bx Y
bx X
bx W
bx V
b0 U
0T
0S
b0 R
b0 Q
b0 P
b0 O
0N
0M
0L
b0 K
b0 J
0I
b0 H
b0 G
b0 F
b0 E
0D
b0 C
b0 B
b0 A
b100 @
b0 ?
b0 >
0=
b0 <
b0 ;
0:
b100 9
b0 8
b0 7
06
05
04
bx 3
x2
x1
bx 0
bx /
bx .
x-
x,
x+
bx *
bx )
bx (
bx '
bx &
bx %
x$
bx #
bx "
bx !
$end
#5000
b0 '
b0 ]
b0 "
b0 a
b0 #
b0 `
b0 /
b0 X
b0 0
b0 W
b0 *
b0 Z
0-
0,
01
0$
0+
b0 !
b0 b
02
b0 3
b0 V
b0 .
b0 Y
b0 %
b0 _
b0 &
b0 ^
b0 (
b0 \
b0 )
b0 [
14
#10000
04
#15000
14
#20000
04
1=
b1010 <
b1010 B
b1010 m
b1 ;
b1 A
b1 l
1:
#25000
b100 (
b100 \
14
#30000
04
b10100 <
b10100 B
b10100 m
b10 ;
b10 A
b10 l
1=
#35000
14
#40000
b10 g
1I
b10100 G
b10100 o
b1010 H
b1010 n
b110011 K
b110011 e
b1 F
b1 j
b10 E
b10 k
b11 J
b10 P
b10 q
b10 s
04
b1000001000000110110011 7
b1000001000000110110011 >
b1000001000000110110011 r
0=
#45000
b11 '
b11 ]
b10 "
b10 a
b1 #
b1 `
b110011 *
b110011 Z
1$
b10 .
b10 Y
b10100 %
b10100 _
b1010 &
b1010 ^
14
#50000
1T
b10 g
1I
bx G
bx o
bx H
bx n
b10011 K
b10011 e
b11 F
b11 j
b101 E
b101 k
b100 J
b101 P
b101 q
b101 s
04
b10100011000001000010011 7
b10100011000001000010011 >
b10100011000001000010011 r
b1000 9
b1000 @
b100 8
b100 ?
#55000
b100 '
b100 ]
b101 "
b101 a
b11 #
b11 `
b10011 *
b10011 Z
12
b101 .
b101 Y
bx %
bx _
bx &
bx ^
b1000 (
b1000 \
b100 )
b100 [
14
#60000
b1 C
b1 i
1T
b0 g
1I
b0 U
b0 f
b11 K
b11 e
b10 R
b10 c
b100 E
b100 k
b101 J
b100 P
b100 q
b100 s
04
b10000011010001010000011 7
b10000011010001010000011 >
b10000011010001010000011 r
b1100 9
b1100 @
b1000 8
b1000 ?
#65000
b101 '
b101 ]
b100 "
b100 a
b10 0
b10 W
b11 *
b11 Z
b1 !
b1 b
b100 .
b100 Y
b1100 (
b1100 \
b1000 )
b1000 [
14
#70000
1L
b1 O
b1 h
b1 p
b0 C
b0 i
1T
0I
b100011 K
b100011 e
b101 E
b101 k
b100 J
b100 P
b100 q
b100 s
04
b10100011010001000100011 7
b10100011010001000100011 >
b10100011010001000100011 r
b10000 9
b10000 @
b1100 8
b1100 ?
#75000
b100 '
b100 ]
b101 "
b101 a
b100011 *
b100011 Z
0$
1+
b0 !
b0 b
b10000 (
b10000 \
b1100 )
b1100 [
14
#80000
b1 U
b1 f
1S
b1 g
0T
0L
b10 O
b10 h
b10 p
b10100 G
b10100 o
b1010 H
b1010 n
b1100011 K
b1100011 e
b0 R
b0 c
b1 F
b1 j
b10 E
b10 k
b1000 J
b1000 P
b1000 q
b1000 s
04
b1000001000010001100011 7
b1000001000010001100011 >
b1000001000010001100011 r
b10100 9
b10100 @
b10000 8
b10000 ?
#85000
b1000 '
b1000 ]
b10 "
b10 a
b1 #
b1 `
b0 0
b0 W
b1100011 *
b1100011 Z
11
0+
02
b1 3
b1 V
b1000 .
b1000 Y
b10100 %
b10100 _
b1010 &
b1010 ^
b10100 (
b10100 \
b10000 )
b10000 [
14
#90000
b0 U
b0 f
1I
0S
b10 g
b0 O
b0 h
b0 p
b110011 K
b110011 e
b11 J
b10 P
b10 q
b10 s
04
b1000001000000110110011 7
b1000001000000110110011 >
b1000001000000110110011 r
15
#95000
b0 '
b0 ]
b0 "
b0 a
b0 #
b0 `
b0 *
b0 Z
01
b0 3
b0 V
b0 .
b0 Y
b0 %
b0 _
b0 &
b0 ^
b0 (
b0 \
b0 )
b0 [
14
#100000
1T
b10 g
1I
bx G
bx o
bx H
bx n
b10011 K
b10011 e
b11 F
b11 j
b101 E
b101 k
b100 J
b101 P
b101 q
b101 s
04
b10100011000001000010011 7
b10100011000001000010011 >
b10100011000001000010011 r
16
05
#105000
14
#110000
1M
b10 C
b10 i
b11 O
b11 h
b11 p
0T
b0 g
1I
b0 H
b0 n
b1101111 K
b1101111 e
b0 F
b0 j
b1000 E
b1000 k
b1 J
b1000 P
b1000 q
b1000 s
04
b100000000000000011101111 7
b100000000000000011101111 >
b100000000000000011101111 r
b11100 9
b11100 @
b11000 8
b11000 ?
06
#115000
b1 '
b1 ]
b1000 "
b1000 a
b1101111 *
b1101111 Z
1,
1$
b10 !
b10 b
b1000 .
b1000 Y
bx %
bx _
b11100 (
b11100 \
b11000 )
b11000 [
14
#120000
1T
1N
0M
b10 C
b10 i
b0 O
b0 h
b0 p
1I
b0 G
b0 o
b1010 H
b1010 n
b1100111 K
b1100111 e
b1 F
b1 j
b0 E
b0 k
b0 P
b0 q
b0 s
04
b1000000011100111 7
b1000000011100111 >
b1000000011100111 r
b100000 9
b100000 @
b11100 8
b11100 ?
#125000
b0 "
b0 a
b1 #
b1 `
b1100111 *
b1100111 Z
1-
0,
12
b0 .
b0 Y
b0 %
b0 _
b1010 &
b1010 ^
b100000 (
b100000 \
b11100 )
b11100 [
14
