rtl/imem.v
module imem (
    input  wire        clk,
    input  wire        rst_n,
    input  wire [31:0] address,
    output wire [31:0] read_data
);

    integer i;
    reg [31:0] mem [0:63];

    always @(posedge clk) begin
        if (!rst_n) begin
            for (i = 0; i < 64; i = i + 1)
                mem[i] <= 32'b0;
        end
    end

    assign read_data = mem[address[31:2]];

endmodule

rtl/if_stage.v
module if_stage (
    input  wire        clk,
    input  wire        rst_n,

    // Load-stall control
    input  wire        pc_write,
    input  wire        if_id_write,

    // Branch flush control
    input  wire        if_id_flush,

    // Branch/JAL/JALR target from EX stage
    input  wire        ex_pc_src,
    input  wire [31:0] ex_pc_target,

    // Outputs to ID stage
    output reg  [31:0] if_id_pc,
    output reg  [31:0] if_id_pc4,
    output reg  [31:0] if_id_instr
);

    // Program Counter
    reg [31:0] pc;

    // Instruction fetched from IMEM
    wire [31:0] instr;

    // Next PC logic
    wire [31:0] pc_next;

    assign pc_next =
        ex_pc_src ? ex_pc_target :
                    (pc + 32'd4);

    //////////////////////////////////////////////////////
    // PC Register
    //////////////////////////////////////////////////////
    always @(posedge clk) begin
        if (!rst_n)
            pc <= 32'b0;

        else if (pc_write)
            pc <= pc_next;
    end

    //////////////////////////////////////////////////////
    // Instruction Memory
    //////////////////////////////////////////////////////
    imem IMEM (
        .clk(clk),
        .rst_n(rst_n),
        .address(pc),
        .read_data(instr)
    );

    //////////////////////////////////////////////////////
    // IF/ID Pipeline Register
    //////////////////////////////////////////////////////
    always @(posedge clk) begin

        // Reset
        if (!rst_n) begin
            if_id_pc    <= 32'b0;
            if_id_pc4   <= 32'b0;
            if_id_instr <= 32'b0;
        end

        // Branch/JAL/JALR Flush
        else if (if_id_flush) begin
            if_id_pc    <= 32'b0;
            if_id_pc4   <= 32'b0;
            if_id_instr <= 32'b0;   // NOP
        end

        // Normal pipeline update
        else if (if_id_write) begin
            if_id_pc    <= pc;
            if_id_pc4   <= pc + 32'd4;
            if_id_instr <= instr;
        end

        // Load-use stall
        else begin
            if_id_pc    <= if_id_pc;
            if_id_pc4   <= if_id_pc4;
            if_id_instr <= if_id_instr;
        end

    end

endmodule

tb/tb_if_stage.v
`timescale 1ns/1ps
`include "../rtl/imem.v"
`include "../rtl/if_stage.v"

module tb_if_stage;

    reg         clk;
    reg         rst_n;

    reg         pc_write;
    reg         if_id_write;
    reg         if_id_flush;

    reg         ex_pc_src;
    reg  [31:0] ex_pc_target;

    wire [31:0] if_id_pc;
    wire [31:0] if_id_pc4;
    wire [31:0] if_id_instr;

    if_stage dut (
        .clk          (clk),
        .rst_n        (rst_n),
        .pc_write     (pc_write),
        .if_id_write  (if_id_write),
        .if_id_flush  (if_id_flush),
        .ex_pc_src    (ex_pc_src),
        .ex_pc_target (ex_pc_target),
        .if_id_pc     (if_id_pc),
        .if_id_pc4    (if_id_pc4),
        .if_id_instr  (if_id_instr)
    );

    always #5 clk = ~clk;

    initial begin
        $dumpfile("../sim/if_stage_wave.vcd");
        $dumpvars(0, tb_if_stage);

        clk = 0;
        rst_n = 0;

        pc_write = 1;
        if_id_write = 1;
        if_id_flush = 0;

        ex_pc_src = 0;
        ex_pc_target = 0;

        #20;
        rst_n = 1;

        dut.IMEM.mem[0] = 32'h00500093;
        dut.IMEM.mem[1] = 32'h00A00113;
        dut.IMEM.mem[2] = 32'h002081B3;
        dut.IMEM.mem[3] = 32'h00320233;
        dut.IMEM.mem[4] = 32'h004282B3;
        dut.IMEM.mem[8] = 32'h11111111;

        #10;
        $display("NORMAL 1 : pc=%0d pc4=%0d instr=%h",
                 if_id_pc, if_id_pc4, if_id_instr);

        #10;
        $display("NORMAL 2 : pc=%0d pc4=%0d instr=%h",
                 if_id_pc, if_id_pc4, if_id_instr);

        #10;
        $display("NORMAL 3 : pc=%0d pc4=%0d instr=%h",
                 if_id_pc, if_id_pc4, if_id_instr);

        pc_write = 0;
        if_id_write = 0;
        #10;
        $display("STALL    : pc=%0d pc4=%0d instr=%h",
                 if_id_pc, if_id_pc4, if_id_instr);

        pc_write = 1;
        if_id_write = 1;
        #10;
        $display("AFTER STALL : pc=%0d pc4=%0d instr=%h",
                 if_id_pc, if_id_pc4, if_id_instr);

        ex_pc_src = 1;
        ex_pc_target = 32'd32;
        if_id_flush = 1;
        #10;
        $display("FLUSH    : pc=%0d pc4=%0d instr=%h",
                 if_id_pc, if_id_pc4, if_id_instr);

        ex_pc_src = 0;
        if_id_flush = 0;
        #10;
        $display("BRANCH TARGET : pc=%0d pc4=%0d instr=%h",
                 if_id_pc, if_id_pc4, if_id_instr);

        #20;
        $finish;
    end

endmodule

sim/if_stage_wave.vcd
$date
	Sun Jun 14 14:51:46 2026
$end
$version
	Icarus Verilog
$end
$timescale
	1ps
$end
$scope module tb_if_stage $end
$var wire 32 ! if_id_pc4 [31:0] $end
$var wire 32 " if_id_pc [31:0] $end
$var wire 32 # if_id_instr [31:0] $end
$var reg 1 $ clk $end
$var reg 1 % ex_pc_src $end
$var reg 32 & ex_pc_target [31:0] $end
$var reg 1 ' if_id_flush $end
$var reg 1 ( if_id_write $end
$var reg 1 ) pc_write $end
$var reg 1 * rst_n $end
$scope module dut $end
$var wire 1 $ clk $end
$var wire 1 % ex_pc_src $end
$var wire 32 + ex_pc_target [31:0] $end
$var wire 1 ' if_id_flush $end
$var wire 1 ( if_id_write $end
$var wire 1 ) pc_write $end
$var wire 1 * rst_n $end
$var wire 32 , pc_next [31:0] $end
$var wire 32 - instr [31:0] $end
$var reg 32 . if_id_instr [31:0] $end
$var reg 32 / if_id_pc [31:0] $end
$var reg 32 0 if_id_pc4 [31:0] $end
$var reg 32 1 pc [31:0] $end
$scope module IMEM $end
$var wire 32 2 address [31:0] $end
$var wire 1 $ clk $end
$var wire 32 3 read_data [31:0] $end
$var wire 1 * rst_n $end
$var integer 32 4 i [31:0] $end
$upscope $end
$upscope $end
$upscope $end
$enddefinitions $end
$comment Show the parameter values. $end
$dumpall
$end
#0
$dumpvars
bx 4
bx 3
bx 2
bx 1
bx 0
bx /
bx .
bx -
bx ,
b0 +
0*
1)
1(
0'
b0 &
0%
0$
bx #
bx "
bx !
$end
#5000
b100 ,
b0 -
b0 3
b0 1
b0 2
b0 #
b0 .
b0 !
b0 0
b0 "
b0 /
b1000000 4
1$
#10000
0$
#15000
b1000000 4
1$
#20000
0$
b10100000000000010010011 -
b10100000000000010010011 3
1*
#25000
b1000 ,
b101000000000000100010011 -
b101000000000000100010011 3
b100 1
b100 2
b10100000000000010010011 #
b10100000000000010010011 .
b100 !
b100 0
1$
#30000
0$
#35000
b1100 ,
b1000001000000110110011 -
b1000001000000110110011 3
b101000000000000100010011 #
b101000000000000100010011 .
b1000 !
b1000 0
b100 "
b100 /
b1000 1
b1000 2
1$
#40000
0$
#45000
b10000 ,
b1100100000001000110011 -
b1100100000001000110011 3
b1100 1
b1100 2
b1000001000000110110011 #
b1000001000000110110011 .
b1100 !
b1100 0
b1000 "
b1000 /
1$
#50000
0$
0(
0)
#55000
1$
#60000
0$
1(
1)
#65000
b10100 ,
b10000101000001010110011 -
b10000101000001010110011 3
b10000 1
b10000 2
b1100100000001000110011 #
b1100100000001000110011 .
b10000 !
b10000 0
b1100 "
b1100 /
1$
#70000
b100000 ,
0$
1'
b100000 &
b100000 +
1%
#75000
b10001000100010001000100010001 -
b10001000100010001000100010001 3
b0 #
b0 .
b0 !
b0 0
b0 "
b0 /
b100000 1
b100000 2
1$
#80000
b100100 ,
0$
0'
0%
#85000
b101000 ,
b0 -
b0 3
b100100 1
b100100 2
b10001000100010001000100010001 #
b10001000100010001000100010001 .
b100100 !
b100100 0
b100000 "
b100000 /
1$
#90000
0$
#95000
b101100 ,
b0 #
b0 .
b101000 !
b101000 0
b100100 "
b100100 /
b101000 1
b101000 2
1$
#100000
0$
#105000
b110000 ,
b101100 1
b101100 2
b101100 !
b101100 0
b101000 "
b101000 /
1$
