rtl/dmem.v
module dmem (
    input  wire        clk,
    input  wire        rst_n,
    input  wire [31:0] address,
    input  wire [31:0] write_data,
    input  wire        write_enable,
    output wire [31:0] read_data
);

    integer i;
    reg [31:0] mem [0:63];

    always @(posedge clk) begin
        if (!rst_n) begin
            for (i = 0; i < 64; i = i + 1)
                mem[i] <= 32'b0;
        end
        else if (write_enable) begin
            if (address[1:0] == 2'b00)
                mem[address[31:2]] <= write_data;
        end
    end

    assign read_data = mem[address[31:2]];

endmodule

rtl/mem_stage.v
module mem_stage (
    input  wire        clk,
    input  wire        rst_n,

    input  wire [31:0] ex_mem_alu_result,
    input  wire [31:0] ex_mem_rdata2,
    input  wire [1:0]  ex_mem_write_back_source,
    input  wire        ex_mem_mem_write,
    input  wire        ex_mem_reg_write,
    input  wire [4:0]  ex_mem_rd,
    input  wire [31:0] ex_mem_pc4,

    output reg  [31:0] mem_wb_alu_result,
    output reg  [31:0] mem_wb_mem_data,
    output reg  [1:0]  mem_wb_write_back_source,
    output reg         mem_wb_reg_write,
    output reg  [4:0]  mem_wb_rd,
    output reg  [31:0] mem_wb_pc4
);

    wire [31:0] dmem_read_data;

    // Data memory
    dmem DMEM (
        .clk(clk),
        .rst_n(rst_n),
        .address(ex_mem_alu_result),
        .write_data(ex_mem_rdata2),
        .write_enable(ex_mem_mem_write),
        .read_data(dmem_read_data)
    );

    // MEM/WB pipeline register
    always @(posedge clk) begin
        if (!rst_n) begin
            mem_wb_alu_result        <= 32'b0;
            mem_wb_mem_data          <= 32'b0;
            mem_wb_write_back_source <= 2'b0;
            mem_wb_reg_write         <= 1'b0;
            mem_wb_rd                <= 5'b0;
            mem_wb_pc4               <= 32'b0;
        end else begin
            mem_wb_alu_result        <= ex_mem_alu_result;
            mem_wb_mem_data          <= dmem_read_data;
            mem_wb_write_back_source <= ex_mem_write_back_source;
            mem_wb_reg_write         <= ex_mem_reg_write;
            mem_wb_rd                <= ex_mem_rd;
            mem_wb_pc4               <= ex_mem_pc4;
        end
    end

endmodule

tb/tb_mem_stage.v
`timescale 1ns/1ps

`include "../rtl/dmem.v"
`include "../rtl/mem_stage.v"

module tb_mem_stage;

    reg         clk;
    reg         rst_n;

    reg  [31:0] ex_mem_alu_result;
    reg  [31:0] ex_mem_rdata2;
    reg  [1:0]  ex_mem_write_back_source;
    reg         ex_mem_mem_write;
    reg         ex_mem_reg_write;
    reg  [4:0]  ex_mem_rd;
    reg  [31:0] ex_mem_pc4;

    wire [31:0] mem_wb_alu_result;
    wire [31:0] mem_wb_mem_data;
    wire [1:0]  mem_wb_write_back_source;
    wire        mem_wb_reg_write;
    wire [4:0]  mem_wb_rd;
    wire [31:0] mem_wb_pc4;

    mem_stage dut (
        .clk                      (clk),
        .rst_n                    (rst_n),

        .ex_mem_alu_result        (ex_mem_alu_result),
        .ex_mem_rdata2            (ex_mem_rdata2),
        .ex_mem_write_back_source (ex_mem_write_back_source),
        .ex_mem_mem_write         (ex_mem_mem_write),
        .ex_mem_reg_write         (ex_mem_reg_write),
        .ex_mem_rd                (ex_mem_rd),
        .ex_mem_pc4               (ex_mem_pc4),

        .mem_wb_alu_result        (mem_wb_alu_result),
        .mem_wb_mem_data          (mem_wb_mem_data),
        .mem_wb_write_back_source (mem_wb_write_back_source),
        .mem_wb_reg_write         (mem_wb_reg_write),
        .mem_wb_rd                (mem_wb_rd),
        .mem_wb_pc4               (mem_wb_pc4)
    );

    always #5 clk = ~clk;

    initial begin
        $dumpfile("../sim/mem_stage_wave.vcd");
        $dumpvars(0, tb_mem_stage);

        clk = 0;
        rst_n = 0;

        ex_mem_alu_result = 0;
        ex_mem_rdata2 = 0;
        ex_mem_write_back_source = 0;
        ex_mem_mem_write = 0;
        ex_mem_reg_write = 0;
        ex_mem_rd = 0;
        ex_mem_pc4 = 0;

        #20;
        rst_n = 1;

        ex_mem_alu_result = 32'd0;
        ex_mem_rdata2 = 32'hAAAA_1111;
        ex_mem_write_back_source = 2'b00;
        ex_mem_mem_write = 1'b1;
        ex_mem_reg_write = 1'b0;
        ex_mem_rd = 5'd0;
        ex_mem_pc4 = 32'd4;
        #10;
        $display("STORE addr=0  write_data=%h mem_data=%h",
                 ex_mem_rdata2, dut.DMEM.mem[0]);

        ex_mem_mem_write = 1'b0;
        ex_mem_alu_result = 32'd0;
        ex_mem_write_back_source = 2'b01;
        ex_mem_reg_write = 1'b1;
        ex_mem_rd = 5'd5;
        ex_mem_pc4 = 32'd8;
        #10;
        $display("LOAD  addr=0  mem_wb_mem_data=%h rd=%0d wb_src=%b reg_write=%b",
                 mem_wb_mem_data, mem_wb_rd,
                 mem_wb_write_back_source, mem_wb_reg_write);

        ex_mem_alu_result = 32'd4;
        ex_mem_rdata2 = 32'hBBBB_2222;
        ex_mem_write_back_source = 2'b00;
        ex_mem_mem_write = 1'b1;
        ex_mem_reg_write = 1'b0;
        ex_mem_rd = 5'd0;
        ex_mem_pc4 = 32'd12;
        #10;
        $display("STORE addr=4  write_data=%h mem_data=%h",
                 ex_mem_rdata2, dut.DMEM.mem[1]);

        ex_mem_mem_write = 1'b0;
        ex_mem_alu_result = 32'd4;
        ex_mem_write_back_source = 2'b01;
        ex_mem_reg_write = 1'b1;
        ex_mem_rd = 5'd6;
        ex_mem_pc4 = 32'd16;
        #10;
        $display("LOAD  addr=4  mem_wb_mem_data=%h rd=%0d wb_src=%b reg_write=%b",
                 mem_wb_mem_data, mem_wb_rd,
                 mem_wb_write_back_source, mem_wb_reg_write);

        ex_mem_alu_result = 32'd100;
        ex_mem_rdata2 = 32'd0;
        ex_mem_write_back_source = 2'b00;
        ex_mem_mem_write = 1'b0;
        ex_mem_reg_write = 1'b1;
        ex_mem_rd = 5'd7;
        ex_mem_pc4 = 32'd20;
        #10;
        $display("ALU PASS      alu_result=%0d rd=%0d wb_src=%b reg_write=%b",
                 mem_wb_alu_result, mem_wb_rd,
                 mem_wb_write_back_source, mem_wb_reg_write);

        ex_mem_alu_result = 32'd0;
        ex_mem_rdata2 = 32'd0;
        ex_mem_write_back_source = 2'b10;
        ex_mem_mem_write = 1'b0;
        ex_mem_reg_write = 1'b1;
        ex_mem_rd = 5'd1;
        ex_mem_pc4 = 32'd104;
        #10;
        $display("PC4 PASS      pc4=%0d rd=%0d wb_src=%b reg_write=%b",
                 mem_wb_pc4, mem_wb_rd,
                 mem_wb_write_back_source, mem_wb_reg_write);

        #20;
        $finish;
    end

endmodule

sim/mem_stage_wave.vcd
$date
	Sun Jun 14 23:16:01 2026
$end
$version
	Icarus Verilog
$end
$timescale
	1ps
$end
$scope module tb_mem_stage $end
$var wire 2 ! mem_wb_write_back_source [1:0] $end
$var wire 1 " mem_wb_reg_write $end
$var wire 5 # mem_wb_rd [4:0] $end
$var wire 32 $ mem_wb_pc4 [31:0] $end
$var wire 32 % mem_wb_mem_data [31:0] $end
$var wire 32 & mem_wb_alu_result [31:0] $end
$var reg 1 ' clk $end
$var reg 32 ( ex_mem_alu_result [31:0] $end
$var reg 1 ) ex_mem_mem_write $end
$var reg 32 * ex_mem_pc4 [31:0] $end
$var reg 5 + ex_mem_rd [4:0] $end
$var reg 32 , ex_mem_rdata2 [31:0] $end
$var reg 1 - ex_mem_reg_write $end
$var reg 2 . ex_mem_write_back_source [1:0] $end
$var reg 1 / rst_n $end
$scope module dut $end
$var wire 1 ' clk $end
$var wire 32 0 ex_mem_alu_result [31:0] $end
$var wire 1 ) ex_mem_mem_write $end
$var wire 32 1 ex_mem_pc4 [31:0] $end
$var wire 5 2 ex_mem_rd [4:0] $end
$var wire 32 3 ex_mem_rdata2 [31:0] $end
$var wire 1 - ex_mem_reg_write $end
$var wire 2 4 ex_mem_write_back_source [1:0] $end
$var wire 1 / rst_n $end
$var wire 32 5 dmem_read_data [31:0] $end
$var reg 32 6 mem_wb_alu_result [31:0] $end
$var reg 32 7 mem_wb_mem_data [31:0] $end
$var reg 32 8 mem_wb_pc4 [31:0] $end
$var reg 5 9 mem_wb_rd [4:0] $end
$var reg 1 " mem_wb_reg_write $end
$var reg 2 : mem_wb_write_back_source [1:0] $end
$scope module DMEM $end
$var wire 32 ; address [31:0] $end
$var wire 1 ' clk $end
$var wire 32 < read_data [31:0] $end
$var wire 1 / rst_n $end
$var wire 32 = write_data [31:0] $end
$var wire 1 ) write_enable $end
$var integer 32 > i [31:0] $end
$upscope $end
$upscope $end
$upscope $end
$enddefinitions $end
$comment Show the parameter values. $end
$dumpall
$end
#0
$dumpvars
bx >
b0 =
bx <
b0 ;
bx :
bx 9
bx 8
bx 7
bx 6
bx 5
b0 4
b0 3
b0 2
b0 1
b0 0
0/
b0 .
0-
b0 ,
b0 +
b0 *
0)
b0 (
0'
bx &
bx %
bx $
bx #
x"
bx !
$end
#5000
b0 5
b0 <
b0 $
b0 8
b0 #
b0 9
0"
b0 !
b0 :
b0 %
b0 7
b0 &
b0 6
b1000000 >
1'
#10000
0'
#15000
b1000000 >
1'
#20000
0'
b100 *
b100 1
1)
b10101010101010100001000100010001 ,
b10101010101010100001000100010001 3
b10101010101010100001000100010001 =
1/
#25000
b10101010101010100001000100010001 5
b10101010101010100001000100010001 <
b100 $
b100 8
1'
#30000
0'
b1000 *
b1000 1
b101 +
b101 2
1-
b1 .
b1 4
0)
#35000
b1000 $
b1000 8
b101 #
b101 9
1"
b1 !
b1 :
b10101010101010100001000100010001 %
b10101010101010100001000100010001 7
1'
#40000
b0 5
b0 <
0'
b1100 *
b1100 1
b0 +
b0 2
0-
1)
b0 .
b0 4
b10111011101110110010001000100010 ,
b10111011101110110010001000100010 3
b10111011101110110010001000100010 =
b100 (
b100 0
b100 ;
#45000
b10111011101110110010001000100010 5
b10111011101110110010001000100010 <
b1100 $
b1100 8
b0 #
b0 9
0"
b0 !
b0 :
b0 %
b0 7
b100 &
b100 6
1'
#50000
0'
b10000 *
b10000 1
b110 +
b110 2
1-
b1 .
b1 4
0)
#55000
b10000 $
b10000 8
b110 #
b110 9
1"
b1 !
b1 :
b10111011101110110010001000100010 %
b10111011101110110010001000100010 7
1'
#60000
b0 5
b0 <
0'
b10100 *
b10100 1
b111 +
b111 2
b0 .
b0 4
b0 ,
b0 3
b0 =
b1100100 (
b1100100 0
b1100100 ;
#65000
b10100 $
b10100 8
b111 #
b111 9
b0 !
b0 :
b0 %
b0 7
b1100100 &
b1100100 6
1'
#70000
b10101010101010100001000100010001 5
b10101010101010100001000100010001 <
0'
b1101000 *
b1101000 1
b1 +
b1 2
b10 .
b10 4
b0 (
b0 0
b0 ;
#75000
b1101000 $
b1101000 8
b1 #
b1 9
b10 !
b10 :
b10101010101010100001000100010001 %
b10101010101010100001000100010001 7
b0 &
b0 6
1'
