rtl/reg_file.v
module reg_file (
    //clk 
    input clk,
    //writes
    input [4:0] address1,address2,
    output reg [31:0] read_data1,read_data2,
    //writes
    input write_enable,
    input [4:0] address3,
    input [31:0] write_data
);

reg [31:0] register [31:0];

//write operation

always @(posedge clk ) begin
    if (write_enable && address3 != 5'd0) begin  // If register is x0 , ignore the write
        register[address3] <= write_data;
    end
end

//read operation
//X0 register is  hardwired to 0
always @(*) begin
    read_data1 = (address1 == 5'd0) ? 32'b0 : register[address1];
    read_data2 = (address2 == 5'd0) ? 32'b0 : register[address2];
end
    
endmodule

tb/tb_reg_file.v
`timescale 1ns/1ps
`include "../rtl/reg_file.v"

module tb_reg_file;

    reg         clk;
    reg  [4:0]  address1;
    reg  [4:0]  address2;
    reg         write_enable;
    reg  [4:0]  address3;
    reg  [31:0] write_data;

    wire [31:0] read_data1;
    wire [31:0] read_data2;

    reg_file dut (
        .clk          (clk),
        .address1     (address1),
        .address2     (address2),
        .read_data1   (read_data1),
        .read_data2   (read_data2),
        .write_enable (write_enable),
        .address3     (address3),
        .write_data   (write_data)
    );

    always #5 clk = ~clk;

    initial begin
        $dumpfile("reg_file_wave.vcd");
        $dumpvars(0, tb_reg_file);

        clk = 0;
        address1 = 0;
        address2 = 0;
        write_enable = 0;
        address3 = 0;
        write_data = 0;

        #10;

        address3 = 5'd1;
        write_data = 32'd100;
        write_enable = 1;
        #10;
        write_enable = 0;

        address1 = 5'd1;
        #10;
        $display("READ x1 : read_data1=%0d", read_data1);

        address3 = 5'd2;
        write_data = 32'd200;
        write_enable = 1;
        #10;
        write_enable = 0;

        address2 = 5'd2;
        #10;
        $display("READ x2 : read_data2=%0d", read_data2);

        address1 = 5'd1;
        address2 = 5'd2;
        #10;
        $display("READ x1/x2 : read_data1=%0d read_data2=%0d",
                 read_data1, read_data2);

        address3 = 5'd0;
        write_data = 32'd999;
        write_enable = 1;
        #10;
        write_enable = 0;

        address1 = 5'd0;
        #10;
        $display("READ x0 : read_data1=%0d", read_data1);

        address3 = 5'd1;
        write_data = 32'd555;
        write_enable = 0;
        #10;

        address1 = 5'd1;
        #10;
        $display("WRITE disabled check x1 : read_data1=%0d", read_data1);

        #20;
        $finish;
    end

endmodule

sim/reg_file_wave.vcd
$date
	Sat Jun 13 19:19:38 2026
$end
$version
	Icarus Verilog
$end
$timescale
	1ps
$end
$scope module tb_reg_file $end
$var wire 32 ! read_data2 [31:0] $end
$var wire 32 " read_data1 [31:0] $end
$var reg 5 # address1 [4:0] $end
$var reg 5 $ address2 [4:0] $end
$var reg 5 % address3 [4:0] $end
$var reg 1 & clk $end
$var reg 32 ' write_data [31:0] $end
$var reg 1 ( write_enable $end
$scope module dut $end
$var wire 5 ) address1 [4:0] $end
$var wire 5 * address2 [4:0] $end
$var wire 5 + address3 [4:0] $end
$var wire 1 & clk $end
$var wire 32 , write_data [31:0] $end
$var wire 1 ( write_enable $end
$var reg 32 - read_data1 [31:0] $end
$var reg 32 . read_data2 [31:0] $end
$upscope $end
$upscope $end
$enddefinitions $end
$comment Show the parameter values. $end
$dumpall
$end
#0
$dumpvars
b0 .
b0 -
b0 ,
b0 +
b0 *
b0 )
0(
b0 '
0&
b0 %
b0 $
b0 #
b0 "
b0 !
$end
#5000
1&
#10000
0&
1(
b1100100 '
b1100100 ,
b1 %
b1 +
#15000
1&
#20000
b1100100 "
b1100100 -
0&
b1 #
b1 )
0(
#25000
1&
#30000
0&
1(
b11001000 '
b11001000 ,
b10 %
b10 +
#35000
1&
#40000
b11001000 !
b11001000 .
0&
b10 $
b10 *
0(
#45000
1&
#50000
0&
#55000
1&
#60000
0&
1(
b1111100111 '
b1111100111 ,
b0 %
b0 +
#65000
1&
#70000
b0 "
b0 -
0&
b0 #
b0 )
0(
#75000
1&
#80000
0&
b1000101011 '
b1000101011 ,
b1 %
b1 +
#85000
1&
#90000
b1100100 "
b1100100 -
0&
b1 #
b1 )
